Workbook

Sheet journey_data
A1: editor | B1: action | C1: lineOfBusiness | D1: channel | E1: product | F1: domain_sequence | G1: domain | H1: sub_domain_sequence | I1: subdomain | J1: business_flow_sequence | K1: business_flow | L1: e2eux_sequence | M1: sequence_uml | N1: e2eux | O1: correlation_id | P1: application | Q1: api | R1: Date Updated | S1: SOX Control | T1: Column1
A2: bb0063 | B2: Add | C2: Mass Markets | D2: Field | E2: Broadband | F2: 2 | G2: Onboard & Activate | H2: 5 | I2: Setup & Activate | J2: 1 | K2: Install Consumer Broadband | L2: 16 | N2: Check Port | O2: 10417 | P2: =IF(Table14[[#This Row],[correlation_id]] = "", "", _xlfn.XLOOKUP(Table14[[#This Row],[correlation_id]], 'ITAP Ref'!A:A, 'ITAP Ref'!C:C, "")) -> G2 | Q2: verifySAMPolicies
A3: bb0063 | B3: Add | C3: Mass Markets | D3: Field | E3: Broadband | F3: 2 | G3: Onboard & Activate | H3: 5 | I3: Setup & Activate | J3: 1 | K3: Install Consumer Broadband | L3: 16 | N3: Check Port | O3: 10417 | P3: =IF(Table14[[#This Row],[correlation_id]] = "", "", _xlfn.XLOOKUP(Table14[[#This Row],[correlation_id]], 'ITAP Ref'!A:A, 'ITAP Ref'!C:C, "")) -> G2 | Q3: verifyCMSPolicies
A4: bb0063 | B4: Add | C4: Mass Markets | D4: Field | E4: Broadband | F4: 2 | G4: Onboard & Activate | H4: 5 | I4: Setup & Activate | J4: 1 | K4: Install Consumer Broadband | L4: 23 | N4: Activate Customer | O4: 10038 | P4: =IF(Table14[[#This Row],[correlation_id]] = "", "", _xlfn.XLOOKUP(Table14[[#This Row],[correlation_id]], 'ITAP Ref'!A:A, 'ITAP Ref'!C:C, "")) -> LS-OMS | Q4: UpdateProductConfiguration
A5: bb0063 | B5: Add | C5: Mass Markets | D5: Care | E5: Broadband | F5: 4 | G5: Service & Support | H5: 1 | I5: Report Issue | J5: 1 | K5: CallBack ATTGuarantee | L5: 1 | N5: Receive Call | O5: 29243 | P5: =IF(Table14[[#This Row],[correlation_id]] = "", "", _xlfn.XLOOKUP(Table14[[#This Row],[correlation_id]], 'ITAP Ref'!A:A, 'ITAP Ref'!C:C, "")) -> HVD-VDI
A6: bb0063 | B6: Add | C6: Mass Markets | D6: Care | E6: Broadband | F6: 4 | G6: Service & Support | H6: 1 | I6: Report Issue | J6: 1 | K6: CallBack ATTGuarantee | L6: 1 | M6: HVD-VDI ->> HVD-VDI Sonus TCCS ->> Sonus TCCS | N6: Receive Call | O6: 26630 | P6: =IF(Table14[[#This Row],[correlation_id]] = "", "", _xlfn.XLOOKUP(Table14[[#This Row],[correlation_id]], 'ITAP Ref'!A:A, 'ITAP Ref'!C:C, "")) -> Sonus TCCS
A7: bb0063 | B7: Add | C7: Mass Markets | D7: Care | E7: Broadband | F7: 4 | G7: Service & Support | H7: 1 | I7: Report Issue | J7: 1 | K7: CallBack ATTGuarantee | L7: 2 | N7: IVR Menu | O7: 10593 | P7: =IF(Table14[[#This Row],[correlation_id]] = "", "", _xlfn.XLOOKUP(Table14[[#This Row],[correlation_id]], 'ITAP Ref'!A:A, 'ITAP Ref'!C:C, "")) -> ISAAC WFE | Q7: POST /restservices/csicustomercareprofile/v2/adapter | R7: 45939
A8: bb0063 | B8: Add | C8: Mass Markets | D8: Field | E8: Broadband | F8: 2 | G8: Onboard & Activate | H8: 5 | I8: Setup & Activate | J8: 1 | K8: Install Consumer Broadband | L8: 16 | N8: Check Port | O8: 9723 | P8: =IF(Table14[[#This Row],[correlation_id]] = "", "", _xlfn.XLOOKUP(Table14[[#This Row],[correlation_id]], 'ITAP Ref'!A:A, 'ITAP Ref'!C:C, "")) -> GRANITE | Q8: updateFiberJack | R8: 45923
A9: bb0063 | B9: Add | C9: Mass Markets | D9: Field | E9: Broadband | F9: 2 | G9: Onboard & Activate | H9: 5 | I9: Setup & Activate | J9: 1 | K9: Install Consumer Broadband | L9: 4 | N9: Select Job / View Comments | O9: 19062 | P9: =IF(Table14[[#This Row],[correlation_id]] = "", "", _xlfn.XLOOKUP(Table14[[#This Row],[correlation_id]], 'ITAP Ref'!A:A, 'ITAP Ref'!C:C, "")) -> EDGE | Q9: UpdateDispatchWorkOrder
A10: bb0063 | B10: Add | C10: Mass Markets | D10: Field | E10: Broadband | F10: 2 | G10: Onboard & Activate | H10: 5 | I10: Setup & Activate | J10: 1 | K10: Install Consumer Broadband | L10: 6 | N10: Arrive on Prem / Update Job | O10: 19062 | P10: =IF(Table14[[#This Row],[correlation_id]] = "", "", _xlfn.XLOOKUP(Table14[[#This Row],[correlation_id]], 'ITAP Ref'!A:A, 'ITAP Ref'!C:C, "")) -> EDGE | Q10: UpdateDispatchWorkOrder
A11: bb0063 | B11: Add | C11: Mass Markets | D11: Field | E11: Broadband | F11: 2 | G11: Onboard & Activate | H11: 5 | I11: Setup & Activate | J11: 1 | K11: Install Consumer Broadband | L11: 24 | N11: Mark Job Complete | O11: 19062 | P11: =IF(Table14[[#This Row],[correlation_id]] = "", "", _xlfn.XLOOKUP(Table14[[#This Row],[correlation_id]], 'ITAP Ref'!A:A, 'ITAP Ref'!C:C, "")) -> EDGE | Q11: UpdateDispatchWorkOrder
A12: bb0063 | B12: Add | C12: Mass Markets | D12: Field | E12: Broadband | F12: 2 | G12: Onboard & Activate | H12: 5 | I12: Setup & Activate | J12: 1 | K12: Install Consumer Broadband | L12: 7 | N12: Review Order w/Customer | O12: 10038 | P12: =IF(Table14[[#This Row],[correlation_id]] = "", "", _xlfn.XLOOKUP(Table14[[#This Row],[correlation_id]], 'ITAP Ref'!A:A, 'ITAP Ref'!C:C, "")) -> LS-OMS | Q12: submitSignature
A13: bb0063 | B13: Add | C13: Mass Markets | D13: Field | E13: Broadband | F13: 2 | G13: Onboard & Activate | H13: 5 | I13: Setup & Activate | J13: 1 | K13: Install Consumer Broadband | L13: 5 | M13: SHM ->> SHM : shmLoginPushCheck | N13: Contact Customer / Verify ETA | O13: 26965 | P13: =IF(Table14[[#This Row],[correlation_id]] = "", "", _xlfn.XLOOKUP(Table14[[#This Row],[correlation_id]], 'ITAP Ref'!A:A, 'ITAP Ref'!C:C, "")) -> SHM | Q13: shmLoginPushCheck | R13: 45937
A14: bb0063 | B14: Add | C14: Mass Markets | D14: Field | E14: Broadband | F14: 2 | G14: Onboard & Activate | H14: 5 | I14: Setup & Activate | J14: 1 | K14: Install Consumer Broadband | L14: 22 | N14: Register RG | O14: 26965 | P14: =IF(Table14[[#This Row],[correlation_id]] = "", "", _xlfn.XLOOKUP(Table14[[#This Row],[correlation_id]], 'ITAP Ref'!A:A, 'ITAP Ref'!C:C, "")) -> SHM | Q14: shmLoginPushCheck | R14: 45937
A15: bb0063 | B15: Add | C15: Mass Markets | D15: Field | E15: Broadband | F15: 2 | G15: Onboard & Activate | H15: 5 | I15: Setup & Activate | J15: 1 | K15: Install Consumer Broadband | L15: 8 | N15: Qualify to Terminal / Verify Assignments | O15: 18781 | P15: =IF(Table14[[#This Row],[correlation_id]] = "", "", _xlfn.XLOOKUP(Table14[[#This Row],[correlation_id]], 'ITAP Ref'!A:A, 'ITAP Ref'!C:C, "")) -> ABPT | Q15: SetlnstLinkClickedService
A16: bb0063 | B16: Add | C16: Mass Markets | D16: Field | E16: Broadband | F16: 2 | G16: Onboard & Activate | H16: 5 | I16: Setup & Activate | J16: 1 | K16: Install Consumer Broadband | L16: 7 | N16: Review Order w/Customer | O16: 10038 | P16: =IF(Table14[[#This Row],[correlation_id]] = "", "", _xlfn.XLOOKUP(Table14[[#This Row],[correlation_id]], 'ITAP Ref'!A:A, 'ITAP Ref'!C:C, "")) -> LS-OMS | Q16: sendSignatureDetails
A17: bb0063 | B17: Add | C17: Mass Markets | D17: Field | E17: Broadband | F17: 2 | G17: Onboard & Activate | H17: 5 | I17: Setup & Activate | J17: 1 | K17: Install Consumer Broadband | L17: 7 | N17: Review Order w/Customer | O17: 10038 | P17: =IF(Table14[[#This Row],[correlation_id]] = "", "", _xlfn.XLOOKUP(Table14[[#This Row],[correlation_id]], 'ITAP Ref'!A:A, 'ITAP Ref'!C:C, "")) -> LS-OMS | Q17: sendOpticalSignatureDetails
A18: bb0063 | B18: Add | C18: Mass Markets | D18: Field | E18: Broadband | F18: 2 | G18: Onboard & Activate | H18: 5 | I18: Setup & Activate | J18: 1 | K18: Install Consumer Broadband | L18: 7 | N18: Review Order w/Customer | O18: 10038 | P18: =IF(Table14[[#This Row],[correlation_id]] = "", "", _xlfn.XLOOKUP(Table14[[#This Row],[correlation_id]], 'ITAP Ref'!A:A, 'ITAP Ref'!C:C, "")) -> LS-OMS | Q18: saveSignature
A19: tm0828 | B19: Add | C19: Mass Markets | D19: Online | E19: Mobility | F19: 1 | G19: Shop & Purchase | H19: 2 | I19: Order Plan/Device | J19: 1 | K19: Purchase Product | L19: 13 | M19: ATTCOM ->> IDPWebSales: IDPWebSales ->> IDPIDM: IDPWebSales ->> IDPBUPS: updateBillingInformation IDPWebSales ->> TLGMOB: | N19: Enter Billing Information | O19: 33847 | P19: =IF(Table14[[#This Row],[correlation_id]] = "", "", _xlfn.XLOOKUP(Table14[[#This Row],[correlation_id]], 'ITAP Ref'!A:A, 'ITAP Ref'!C:C, "")) -> IDP-BUPS | Q19: updateBillingInformation
A20: bb0063 | B20: Add | C20: Mass Markets | D20: Field | E20: Broadband | F20: 2 | G20: Onboard & Activate | H20: 5 | I20: Setup & Activate | J20: 1 | K20: Install Consumer Broadband | L20: 7 | N20: Review Order w/Customer | O20: 10038 | P20: =IF(Table14[[#This Row],[correlation_id]] = "", "", _xlfn.XLOOKUP(Table14[[#This Row],[correlation_id]], 'ITAP Ref'!A:A, 'ITAP Ref'!C:C, "")) -> LS-OMS | Q20: retrieveSignature
A21: bb0063 | B21: Add | C21: Mass Markets | D21: Field | E21: Broadband | F21: 2 | G21: Onboard & Activate | H21: 5 | I21: Setup & Activate | J21: 1 | K21: Install Consumer Broadband | L21: 16 | N21: Check Port | O21: 10417 | P21: =IF(Table14[[#This Row],[correlation_id]] = "", "", _xlfn.XLOOKUP(Table14[[#This Row],[correlation_id]], 'ITAP Ref'!A:A, 'ITAP Ref'!C:C, "")) -> G2 | Q21: restorePolicyData
A22: bb0063 | B22: Add | C22: Mass Markets | D22: Field | E22: Broadband | F22: 2 | G22: Onboard & Activate | H22: 5 | I22: Setup & Activate | J22: 1 | K22: Install Consumer Broadband | L22: 3 | N22: Review Jobs | O22: 27267 | P22: =IF(Table14[[#This Row],[correlation_id]] = "", "", _xlfn.XLOOKUP(Table14[[#This Row],[correlation_id]], 'ITAP Ref'!A:A, 'ITAP Ref'!C:C, "")) -> (FED) - FASTBPM | Q22: POST /restservices/getLconDetails | R22: 45953
A23: bb0063 | B23: Add | C23: Mass Markets | D23: Field | E23: Broadband | F23: 2 | G23: Onboard & Activate | H23: 5 | I23: Setup & Activate | J23: 1 | K23: Install Consumer Broadband | L23: 4 | N23: Select Job / View Comments | O23: 27267 | P23: =IF(Table14[[#This Row],[correlation_id]] = "", "", _xlfn.XLOOKUP(Table14[[#This Row],[correlation_id]], 'ITAP Ref'!A:A, 'ITAP Ref'!C:C, "")) -> (FED) - FASTBPM | Q23: POST /restservices/getLconDetails | R23: 45953
A24: bb0063 | B24: Add | C24: Mass Markets | D24: Field | E24: Broadband | F24: 2 | G24: Onboard & Activate | H24: 5 | I24: Setup & Activate | J24: 1 | K24: Install Consumer Broadband | L24: 7 | N24: Review Order w/Customer | O24: 27267 | P24: =IF(Table14[[#This Row],[correlation_id]] = "", "", _xlfn.XLOOKUP(Table14[[#This Row],[correlation_id]], 'ITAP Ref'!A:A, 'ITAP Ref'!C:C, "")) -> (FED) - FASTBPM | Q24: POST /restservices/getLconDetails | R24: 45953
A25: bb0063 | B25: Add | C25: Mass Markets | D25: Field | E25: Broadband | F25: 2 | G25: Onboard & Activate | H25: 5 | I25: Setup & Activate | J25: 1 | K25: Install Consumer Broadband | L25: 15 | N25: Select ONT | O25: 14311 | P25: =IF(Table14[[#This Row],[correlation_id]] = "", "", _xlfn.XLOOKUP(Table14[[#This Row],[correlation_id]], 'ITAP Ref'!A:A, 'ITAP Ref'!C:C, "")) -> LSBBT | Q25: ontActivation
A26: bb0063 | B26: Add | C26: Mass Markets | D26: Field | E26: Broadband | F26: 2 | G26: Onboard & Activate | H26: 5 | I26: Setup & Activate | J26: 1 | K26: Install Consumer Broadband | L26: 15 | N26: Select ONT | O26: 14311 | P26: =IF(Table14[[#This Row],[correlation_id]] = "", "", _xlfn.XLOOKUP(Table14[[#This Row],[correlation_id]], 'ITAP Ref'!A:A, 'ITAP Ref'!C:C, "")) -> LSBBT | Q26: integratedOntActivation
A27: bb0063 | B27: Add | C27: Mass Markets | D27: Field | E27: Broadband | F27: 2 | G27: Onboard & Activate | H27: 5 | I27: Setup & Activate | J27: 1 | K27: Install Consumer Broadband | L27: 3 | N27: Review Jobs | O27: 19062 | P27: =IF(Table14[[#This Row],[correlation_id]] = "", "", _xlfn.XLOOKUP(Table14[[#This Row],[correlation_id]], 'ITAP Ref'!A:A, 'ITAP Ref'!C:C, "")) -> EDGE | Q27: InquireDispatchWorkOrderList
A28: bb0063 | B28: Add | C28: Mass Markets | D28: Field | E28: Broadband | F28: 2 | G28: Onboard & Activate | H28: 5 | I28: Setup & Activate | J28: 1 | K28: Install Consumer Broadband | L28: 4 | N28: Select Job / View Comments | O28: 19062 | P28: =IF(Table14[[#This Row],[correlation_id]] = "", "", _xlfn.XLOOKUP(Table14[[#This Row],[correlation_id]], 'ITAP Ref'!A:A, 'ITAP Ref'!C:C, "")) -> EDGE | Q28: InquireDispatchWorkOrderList
A29: bb0063 | B29: Add | C29: Mass Markets | D29: Field | E29: Broadband | F29: 2 | G29: Onboard & Activate | H29: 5 | I29: Setup & Activate | J29: 1 | K29: Install Consumer Broadband | L29: 7 | N29: Review Order w/Customer | O29: 19062 | P29: =IF(Table14[[#This Row],[correlation_id]] = "", "", _xlfn.XLOOKUP(Table14[[#This Row],[correlation_id]], 'ITAP Ref'!A:A, 'ITAP Ref'!C:C, "")) -> EDGE | Q29: InquireDispatchWorkOrderList
A30: bb0063 | B30: Add | C30: Mass Markets | D30: Field | E30: Broadband | F30: 2 | G30: Onboard & Activate | H30: 5 | I30: Setup & Activate | J30: 1 | K30: Install Consumer Broadband | L30: 8 | N30: Qualify to Terminal / Verify Assignments | O30: 18781 | P30: =IF(Table14[[#This Row],[correlation_id]] = "", "", _xlfn.XLOOKUP(Table14[[#This Row],[correlation_id]], 'ITAP Ref'!A:A, 'ITAP Ref'!C:C, "")) -> ABPT | Q30: GetTerminalAppearancesService
A31: bb0063 | B31: Add | C31: Mass Markets | D31: Field | E31: Broadband | F31: 2 | G31: Onboard & Activate | H31: 5 | I31: Setup & Activate | J31: 1 | K31: Install Consumer Broadband | L31: 8 | N31: Qualify to Terminal / Verify Assignments | O31: 18781 | P31: =IF(Table14[[#This Row],[correlation_id]] = "", "", _xlfn.XLOOKUP(Table14[[#This Row],[correlation_id]], 'ITAP Ref'!A:A, 'ITAP Ref'!C:C, "")) -> ABPT | Q31: GetSparePortPairsService
A32: bb0063 | B32: Add | C32: Mass Markets | D32: Field | E32: Broadband | F32: 2 | G32: Onboard & Activate | H32: 5 | I32: Setup & Activate | J32: 1 | K32: Install Consumer Broadband | L32: 12 | N32: Add Port to Door | O32: 18781 | P32: =IF(Table14[[#This Row],[correlation_id]] = "", "", _xlfn.XLOOKUP(Table14[[#This Row],[correlation_id]], 'ITAP Ref'!A:A, 'ITAP Ref'!C:C, "")) -> ABPT | Q32: GetSparePortPairsService
A33: bb0063 | B33: Add | C33: Mass Markets | D33: Field | E33: Broadband | F33: 2 | G33: Onboard & Activate | H33: 5 | I33: Setup & Activate | J33: 1 | K33: Install Consumer Broadband | L33: 8 | N33: Qualify to Terminal / Verify Assignments | O33: 18781 | P33: =IF(Table14[[#This Row],[correlation_id]] = "", "", _xlfn.XLOOKUP(Table14[[#This Row],[correlation_id]], 'ITAP Ref'!A:A, 'ITAP Ref'!C:C, "")) -> ABPT | Q33: GetSparePairsService
A34: bb0063 | B34: Add | C34: Mass Markets | D34: Care | E34: Broadband | F34: 4 | G34: Service & Support | H34: 1 | I34: Report Issue | J34: 1 | K34: CallBack ATTGuarantee | L34: 2 | N34: IVR Menu | O34: 10593 | P34: =IF(Table14[[#This Row],[correlation_id]] = "", "", _xlfn.XLOOKUP(Table14[[#This Row],[correlation_id]], 'ITAP Ref'!A:A, 'ITAP Ref'!C:C, "")) -> ISAAC WFE | Q34: GET /restservices/eco-control/v1/integrations/subscribers/details | R34: 45953
A35: bb0063 | B35: Add | C35: Mass Markets | D35: Care | E35: Broadband | F35: 4 | G35: Service & Support | H35: 1 | I35: Report Issue | J35: 1 | K35: CallBack ATTGuarantee | L35: 2 | N35: IVR Menu | O35: 31468 | P35: =IF(Table14[[#This Row],[correlation_id]] = "", "", _xlfn.XLOOKUP(Table14[[#This Row],[correlation_id]], 'ITAP Ref'!A:A, 'ITAP Ref'!C:C, "")) -> IDP-Cloud-CG
A36: bb0063 | B36: Add | C36: Mass Markets | D36: Field | E36: Broadband | F36: 2 | G36: Onboard & Activate | H36: 5 | I36: Setup & Activate | J36: 1 | K36: Install Consumer Broadband | L36: 12 | N36: Add Port to Door | O36: 18781 | P36: =IF(Table14[[#This Row],[correlation_id]] = "", "", _xlfn.XLOOKUP(Table14[[#This Row],[correlation_id]], 'ITAP Ref'!A:A, 'ITAP Ref'!C:C, "")) -> ABPT | Q36: GetSparePairsService
A37: bb0063 | B37: Add | C37: Mass Markets | D37: Field | E37: Broadband | F37: 2 | G37: Onboard & Activate | H37: 5 | I37: Setup & Activate | J37: 1 | K37: Install Consumer Broadband | L37: 3 | N37: Review Jobs | O37: 27531 | P37: =IF(Table14[[#This Row],[correlation_id]] = "", "", _xlfn.XLOOKUP(Table14[[#This Row],[correlation_id]], 'ITAP Ref'!A:A, 'ITAP Ref'!C:C, "")) -> Digital IDP | Q37: getJobsByUid | R37: 45953
A38: bb0063 | B38: Add | C38: Mass Markets | D38: Field | E38: Broadband | F38: 2 | G38: Onboard & Activate | H38: 5 | I38: Setup & Activate | J38: 1 | K38: Install Consumer Broadband | L38: 8 | N38: Qualify to Terminal / Verify Assignments | O38: 18781 | P38: =IF(Table14[[#This Row],[correlation_id]] = "", "", _xlfn.XLOOKUP(Table14[[#This Row],[correlation_id]], 'ITAP Ref'!A:A, 'ITAP Ref'!C:C, "")) -> ABPT | Q38: GetJobDetailsService
A39: bb0063 | B39: Add | C39: Mass Markets | D39: Field | E39: Broadband | F39: 2 | G39: Onboard & Activate | H39: 5 | I39: Setup & Activate | J39: 1 | K39: Install Consumer Broadband | L39: 9 | N39: Qualify Terminal / True Test | O39: 14311 | P39: =IF(Table14[[#This Row],[correlation_id]] = "", "", _xlfn.XLOOKUP(Table14[[#This Row],[correlation_id]], 'ITAP Ref'!A:A, 'ITAP Ref'!C:C, "")) -> LSBBT | Q39: getFiberTrueTestResults
A40: tm0828 | B40: Add | C40: Mass Markets | D40: Online | E40: Mobility | F40: 1 | G40: Shop & Purchase | H40: 2 | I40: Order Plan/Device | J40: 1 | K40: Purchase Product | L40: 1 | N40: Go to att.com | O40: 31548 | P40: =IF(Table14[[#This Row],[correlation_id]] = "", "", _xlfn.XLOOKUP(Table14[[#This Row],[correlation_id]], 'ITAP Ref'!A:A, 'ITAP Ref'!C:C, "")) -> IDP-Upper Funnel Cloud | Q40: recommendationms
A41: bb0063 | B41: Add | C41: Mass Markets | D41: Care | E41: Broadband | F41: 4 | G41: Service & Support | H41: 1 | I41: Report Issue | J41: 1 | K41: CallBack ATTGuarantee | L41: 2 | N41: IVR Menu | O41: 26150 | P41: =IF(Table14[[#This Row],[correlation_id]] = "", "", _xlfn.XLOOKUP(Table14[[#This Row],[correlation_id]], 'ITAP Ref'!A:A, 'ITAP Ref'!C:C, "")) -> ATT CCT AEP
A42: bb0063 | B42: Add | C42: Mass Markets | D42: Care | E42: Broadband | F42: 4 | G42: Service & Support | H42: 1 | I42: Report Issue | J42: 1 | K42: CallBack ATTGuarantee | L42: 2 | M42: IVR ->> ATT CCT AEP IVR ->> ATT CCT SAG IVR ->> CCSF IVR ->> CCT ATT IPCS IVR ->> CSI - Customer Care: InquireUnifiedCustomerProfileByServiceLocation IVR ->> ECO Suite: /api/integrations/subscribers/details IVR ->> IDP - Customer Graph IVR ->> ISAAC WFE: GET /restservices/eco-control/v1/integrations/subscribers/details IVR->>ISAAC WFE: POST /restservices/csicustomercareprofile/v2/adapter IVR - >> LS CRM IVR->> Nimbus IVR ->> OPUS-C IVR->> ATT CCT APIGEE IVR ->> DialogFlow IVR ->> IDP-Chat VA ANDi IVR->> PC-GCP BI | N42: IVR Menu | O42: 26215 | P42: =IF(Table14[[#This Row],[correlation_id]] = "", "", _xlfn.XLOOKUP(Table14[[#This Row],[correlation_id]], 'ITAP Ref'!A:A, 'ITAP Ref'!C:C, "")) -> ATT CCT Service Access Gateway
A43: bb0063 | B43: Add | C43: Mass Markets | D43: Care | E43: Broadband | F43: 4 | G43: Service & Support | H43: 1 | I43: Report Issue | J43: 1 | K43: CallBack ATTGuarantee | L43: 2 | N43: IVR Menu | O43: 25363 | P43: =IF(Table14[[#This Row],[correlation_id]] = "", "", _xlfn.XLOOKUP(Table14[[#This Row],[correlation_id]], 'ITAP Ref'!A:A, 'ITAP Ref'!C:C, "")) -> CCT ATT IPCS
A44: bb0063 | B44: Add | C44: Mass Markets | D44: Care | E44: Broadband | F44: 4 | G44: Service & Support | H44: 1 | I44: Report Issue | J44: 1 | K44: CallBack ATTGuarantee | L44: 2 | N44: IVR Menu | O44: 34361 | P44: =IF(Table14[[#This Row],[correlation_id]] = "", "", _xlfn.XLOOKUP(Table14[[#This Row],[correlation_id]], 'ITAP Ref'!A:A, 'ITAP Ref'!C:C, "")) -> ECO USP | R44: ISAAC WFE API
A45: bb0063 | B45: Add | C45: Mass Markets | D45: Care | E45: Broadband | F45: 4 | G45: Service & Support | H45: 1 | I45: Report Issue | J45: 1 | K45: CallBack ATTGuarantee | L45: 2 | N45: IVR Menu | O45: 14311 | P45: =IF(Table14[[#This Row],[correlation_id]] = "", "", _xlfn.XLOOKUP(Table14[[#This Row],[correlation_id]], 'ITAP Ref'!A:A, 'ITAP Ref'!C:C, "")) -> LSBBT
A46: bb0063 | B46: Add | C46: Mass Markets | D46: Care | E46: Broadband | F46: 4 | G46: Service & Support | H46: 1 | I46: Report Issue | J46: 1 | K46: CallBack ATTGuarantee | L46: 3 | M46: IVR ->> ATT CCT APIGEE IVR ->> DialogFlow IVR ->> IDP-Chat VA ANDi IVR ->> PC-GCP BI | N46: Retrieve Customer Info & Call Routing | O46: 30793 | P46: =IF(Table14[[#This Row],[correlation_id]] = "", "", _xlfn.XLOOKUP(Table14[[#This Row],[correlation_id]], 'ITAP Ref'!A:A, 'ITAP Ref'!C:C, "")) -> ATT CCT APIGEE
A47: bb0063 | B47: Add | C47: Mass Markets | D47: Care | E47: Broadband | F47: 4 | G47: Service & Support | H47: 1 | I47: Report Issue | J47: 1 | K47: CallBack ATTGuarantee | L47: 3 | N47: Retrieve Customer Info & Call Routing | O47: 31036 | P47: =IF(Table14[[#This Row],[correlation_id]] = "", "", _xlfn.XLOOKUP(Table14[[#This Row],[correlation_id]], 'ITAP Ref'!A:A, 'ITAP Ref'!C:C, "")) -> DialogFlow
A48: bb0063 | B48: Add | C48: Mass Markets | D48: Care | E48: Broadband | F48: 4 | G48: Service & Support | H48: 1 | I48: Report Issue | J48: 1 | K48: CallBack ATTGuarantee | L48: 3 | N48: Retrieve Customer Info & Call Routing | O48: 30063 | P48: =IF(Table14[[#This Row],[correlation_id]] = "", "", _xlfn.XLOOKUP(Table14[[#This Row],[correlation_id]], 'ITAP Ref'!A:A, 'ITAP Ref'!C:C, "")) -> IDP- Chat VA ANDi
A49: bb0063 | B49: Add | C49: Mass Markets | D49: Field | E49: Broadband | F49: 2 | G49: Onboard & Activate | H49: 5 | I49: Setup & Activate | J49: 1 | K49: Install Consumer Broadband | L49: 14 | M49: VIAVI ->> LSBBT : getFiberTrueTestResults | N49: Test Light Levels | O49: 14311 | P49: =IF(Table14[[#This Row],[correlation_id]] = "", "", _xlfn.XLOOKUP(Table14[[#This Row],[correlation_id]], 'ITAP Ref'!A:A, 'ITAP Ref'!C:C, "")) -> LSBBT | Q49: getFiberTrueTestResults
A50: bb0063 | B50: Add | C50: Mass Markets | D50: Field | E50: Broadband | F50: 2 | G50: Onboard & Activate | H50: 5 | I50: Setup & Activate | J50: 1 | K50: Install Consumer Broadband | L50: 17 | N50: Perform Final True Test | O50: 14311 | P50: =IF(Table14[[#This Row],[correlation_id]] = "", "", _xlfn.XLOOKUP(Table14[[#This Row],[correlation_id]], 'ITAP Ref'!A:A, 'ITAP Ref'!C:C, "")) -> LSBBT | Q50: getFiberTrueTestResults
A51: bb0063 | B51: Add | C51: Mass Markets | D51: Field | E51: Broadband | F51: 2 | G51: Onboard & Activate | H51: 5 | I51: Setup & Activate | J51: 1 | K51: Install Consumer Broadband | L51: 8 | N51: Qualify to Terminal / Verify Assignments | O51: 18781 | P51: =IF(Table14[[#This Row],[correlation_id]] = "", "", _xlfn.XLOOKUP(Table14[[#This Row],[correlation_id]], 'ITAP Ref'!A:A, 'ITAP Ref'!C:C, "")) -> ABPT | Q51: GetFiberAssistTicketldService
A52: bb0063 | B52: Add | C52: Mass Markets | D52: Field | E52: Broadband | F52: 2 | G52: Onboard & Activate | H52: 5 | I52: Setup & Activate | J52: 1 | K52: Install Consumer Broadband | L52: 12 | N52: Add Port to Door | O52: 18781 | P52: =IF(Table14[[#This Row],[correlation_id]] = "", "", _xlfn.XLOOKUP(Table14[[#This Row],[correlation_id]], 'ITAP Ref'!A:A, 'ITAP Ref'!C:C, "")) -> ABPT | Q52: GetDpuPortService
A53: bb0063 | B53: Add | C53: Mass Markets | D53: Field | E53: Broadband | F53: 2 | G53: Onboard & Activate | H53: 5 | I53: Setup & Activate | J53: 1 | K53: Install Consumer Broadband | L53: 3 | N53: Review Jobs | O53: 19062 | P53: =IF(Table14[[#This Row],[correlation_id]] = "", "", _xlfn.XLOOKUP(Table14[[#This Row],[correlation_id]], 'ITAP Ref'!A:A, 'ITAP Ref'!C:C, "")) -> EDGE | Q53: GETDETAILS
A54: bb0063 | B54: Add | C54: Mass Markets | D54: Field | E54: Broadband | F54: 2 | G54: Onboard & Activate | H54: 5 | I54: Setup & Activate | J54: 1 | K54: Install Consumer Broadband | L54: 4 | N54: Select Job / View Comments | O54: 19062 | P54: =IF(Table14[[#This Row],[correlation_id]] = "", "", _xlfn.XLOOKUP(Table14[[#This Row],[correlation_id]], 'ITAP Ref'!A:A, 'ITAP Ref'!C:C, "")) -> EDGE | Q54: GETDETAILS
A55: bb0063 | B55: Add | C55: Mass Markets | D55: Field | E55: Broadband | F55: 2 | G55: Onboard & Activate | H55: 5 | I55: Setup & Activate | J55: 1 | K55: Install Consumer Broadband | L55: 7 | N55: Review Order w/Customer | O55: 19062 | P55: =IF(Table14[[#This Row],[correlation_id]] = "", "", _xlfn.XLOOKUP(Table14[[#This Row],[correlation_id]], 'ITAP Ref'!A:A, 'ITAP Ref'!C:C, "")) -> EDGE | Q55: GETDETAILS
A56: bb0063 | B56: Add | C56: Mass Markets | D56: Care | E56: Broadband | F56: 4 | G56: Service & Support | H56: 1 | I56: Report Issue | J56: 1 | K56: CallBack ATTGuarantee | L56: 3 | N56: Retrieve Customer Info & Call Routing | O56: 31445 | P56: =IF(Table14[[#This Row],[correlation_id]] = "", "", _xlfn.XLOOKUP(Table14[[#This Row],[correlation_id]], 'ITAP Ref'!A:A, 'ITAP Ref'!C:C, "")) -> PC-GCP BI
A57: bb0063 | B57: Add | C57: Mass Markets | D57: Care | E57: Broadband | F57: 4 | G57: Service & Support | H57: 1 | I57: Report Issue | J57: 1 | K57: CallBack ATTGuarantee | L57: 4 | N57: Offer / Schedule Callback | O57: 21359 | P57: =IF(Table14[[#This Row],[correlation_id]] = "", "", _xlfn.XLOOKUP(Table14[[#This Row],[correlation_id]], 'ITAP Ref'!A:A, 'ITAP Ref'!C:C, "")) -> ATT CCTP MC VHT FRAME | Q57: CheckVhtSingleCtiEligibility
A58: em114j | B58: Add | C58: Mass Markets | D58: MVNO | E58: Wholesale Mobility | F58: 2 | G58: Use & Manage | H58: 1 | I58: Change Settings & Prefrences | J58: 2 | K58: Triage / MVNO Care | L58: 1 | N58: Assess Porting Issues | O58: 20188 | P58: =IF(Table14[[#This Row],[correlation_id]] = "", "", _xlfn.XLOOKUP(Table14[[#This Row],[correlation_id]], 'ITAP Ref'!A:A, 'ITAP Ref'!C:C, "")) -> CSI - Network Management | Q58: /service=com.att.csi.m2e.CancelPort/version=1012.5.11/envContext=PROD/routeOffer=AW2P01 | R58: 45953
A59: bb0063 | B59: Add | C59: Mass Markets | D59: Care | E59: Broadband | F59: 4 | G59: Service & Support | H59: 1 | I59: Report Issue | J59: 1 | K59: CallBack ATTGuarantee | L59: 4 | N59: Offer / Schedule Callback | O59: 21359 | P59: =IF(Table14[[#This Row],[correlation_id]] = "", "", _xlfn.XLOOKUP(Table14[[#This Row],[correlation_id]], 'ITAP Ref'!A:A, 'ITAP Ref'!C:C, "")) -> ATT CCTP MC VHT FRAME | Q59: CheckVhtGenesysEligibility
A60: bb0063 | B60: Add | C60: Mass Markets | D60: Care | E60: Broadband | F60: 4 | G60: Service & Support | H60: 1 | I60: Report Issue | J60: 1 | K60: CallBack ATTGuarantee | L60: 4 | M60: ATT CCT AEP->> ATT CCTP NMC VHT FRAME: CheckVhtSingleCtiEligibility ATT CCT AEP->> ATT CCTP NMC VHT FRAME: CheckVhtGenesysEligibility ATT CCT AEP->> ATT CCTP NMC VHT FRAME: CheckVhtEligibility | N60: Offer / Schedule Callback | O60: 21359 | P60: =IF(Table14[[#This Row],[correlation_id]] = "", "", _xlfn.XLOOKUP(Table14[[#This Row],[correlation_id]], 'ITAP Ref'!A:A, 'ITAP Ref'!C:C, "")) -> ATT CCTP MC VHT FRAME | Q60: CheckVhtEligibility
A61: bb0063 | B61: Add | C61: Mass Markets | D61: Field | E61: Broadband | F61: 2 | G61: Onboard & Activate | H61: 5 | I61: Setup & Activate | J61: 1 | K61: Install Consumer Broadband | L61: 8 | N61: Qualify to Terminal / Verify Assignments | O61: 18781 | P61: =IF(Table14[[#This Row],[correlation_id]] = "", "", _xlfn.XLOOKUP(Table14[[#This Row],[correlation_id]], 'ITAP Ref'!A:A, 'ITAP Ref'!C:C, "")) -> ABPT | Q61: GetCopperFacilitieslnfoService
A62: tm0828 | B62: Add | C62: Mass Markets | D62: Online | E62: Mobility | F62: 1 | G62: Shop & Purchase | H62: 2 | I62: Order Plan/Device | J62: 1 | K62: Purchase Product | L62: 2 | N62: Select "Wireless" | O62: 31548 | P62: =IF(Table14[[#This Row],[correlation_id]] = "", "", _xlfn.XLOOKUP(Table14[[#This Row],[correlation_id]], 'ITAP Ref'!A:A, 'ITAP Ref'!C:C, "")) -> IDP-Upper Funnel Cloud | Q62: online-sales-orchestration
A63: bb0063 | B63: Add | C63: Mass Markets | D63: Field | E63: Broadband | F63: 2 | G63: Onboard & Activate | H63: 5 | I63: Setup & Activate | J63: 1 | K63: Install Consumer Broadband | L63: 8 | N63: Qualify to Terminal / Verify Assignments | O63: 18781 | P63: =IF(Table14[[#This Row],[correlation_id]] = "", "", _xlfn.XLOOKUP(Table14[[#This Row],[correlation_id]], 'ITAP Ref'!A:A, 'ITAP Ref'!C:C, "")) -> ABPT | Q63: GetCablesOnTicketService
A64: bb0063 | B64: Add | C64: Corporate Systems | D64: Human Resources | E64: SOX | F64: 1 | G64: Onboard | H64: 5 | I64: Hiring Guidelines | J64: 1 | K64: Onboard New Hire to Payroll | L64: 5 | M64: Workday ->> INFOR: Intergration 267 | N64: Determine Calculation Group | O64: 30763 | P64: =IF(Table14[[#This Row],[correlation_id]] = "", "", _xlfn.XLOOKUP(Table14[[#This Row],[correlation_id]], 'ITAP Ref'!A:A, 'ITAP Ref'!C:C, "")) -> Infor | Q64: Intergration 267 | R64: Confirmed
A65: bb0063 | B65: Add | C65: Corporate Systems | D65: Human Resources | E65: SOX | F65: 1 | G65: Onboard | H65: 5 | I65: Hiring Guidelines | J65: 1 | K65: Onboard New Hire to Payroll | L65: 7 | M65: INFOR ->> Workday: Integration 211 | N65: Convert Time Code to Pay Component | O65: 30763 | P65: =IF(Table14[[#This Row],[correlation_id]] = "", "", _xlfn.XLOOKUP(Table14[[#This Row],[correlation_id]], 'ITAP Ref'!A:A, 'ITAP Ref'!C:C, "")) -> Infor | Q65: Intergration 211 | R65: POG no API
A66: bb0063 | B66: Add | C66: Corporate Systems | D66: Human Resources | E66: SOX | F66: 1 | G66: Onboard | H66: 5 | I66: Hiring Guidelines | J66: 1 | K66: Onboard New Hire to Payroll | L66: 10 | M66: Workday ->> CorpFin-GL: Integration 77 | N66: Payroll to General Ledger | O66: 32412 | P66: =IF(Table14[[#This Row],[correlation_id]] = "", "", _xlfn.XLOOKUP(Table14[[#This Row],[correlation_id]], 'ITAP Ref'!A:A, 'ITAP Ref'!C:C, "")) -> OGSI - GL | Q66: Integration 77
A67: bb0063 | B67: Add | C67: Mass Markets | D67: Field | E67: Broadband | F67: 2 | G67: Onboard & Activate | H67: 5 | I67: Setup & Activate | J67: 1 | K67: Install Consumer Broadband | L67: 8 | N67: Qualify to Terminal / Verify Assignments | O67: 18781 | P67: =IF(Table14[[#This Row],[correlation_id]] = "", "", _xlfn.XLOOKUP(Table14[[#This Row],[correlation_id]], 'ITAP Ref'!A:A, 'ITAP Ref'!C:C, "")) -> ABPT | Q67: GetAvailableFiberStrandsService
A68: bb0063 | B68: Add | C68: Mass Markets | D68: Field | E68: Broadband | F68: 2 | G68: Onboard & Activate | H68: 5 | I68: Setup & Activate | J68: 1 | K68: Install Consumer Broadband | L68: 4 | N68: Select Job / View Comments | O68: 10038 | P68: =IF(Table14[[#This Row],[correlation_id]] = "", "", _xlfn.XLOOKUP(Table14[[#This Row],[correlation_id]], 'ITAP Ref'!A:A, 'ITAP Ref'!C:C, "")) -> LS-OMS | Q68: GetAvailableAppointments
A69: bb0063 | B69: Add | C69: Mass Markets | D69: Field | E69: Broadband | F69: 2 | G69: Onboard & Activate | H69: 5 | I69: Setup & Activate | J69: 1 | K69: Install Consumer Broadband | L69: 11 | N69: Place Fiber Connectors | O69: 9723 | P69: =IF(Table14[[#This Row],[correlation_id]] = "", "", _xlfn.XLOOKUP(Table14[[#This Row],[correlation_id]], 'ITAP Ref'!A:A, 'ITAP Ref'!C:C, "")) -> GRANITE | Q69: FiberJackUpdateRebuildService
A70: bb0063 | B70: Add | C70: Mass Markets | D70: Field | E70: Broadband | F70: 2 | G70: Onboard & Activate | H70: 5 | I70: Setup & Activate | J70: 1 | K70: Install Consumer Broadband | L70: 16 | N70: Check Port | O70: 9723 | P70: =IF(Table14[[#This Row],[correlation_id]] = "", "", _xlfn.XLOOKUP(Table14[[#This Row],[correlation_id]], 'ITAP Ref'!A:A, 'ITAP Ref'!C:C, "")) -> GRANITE | Q70: FiberJacklndicatorService
A71: bb0063 | B71: Add | C71: Mass Markets | D71: Field | E71: Broadband | F71: 2 | G71: Onboard & Activate | H71: 5 | I71: Setup & Activate | J71: 1 | K71: Install Consumer Broadband | L71: 11 | N71: Place Fiber Connectors | O71: 9723 | P71: =IF(Table14[[#This Row],[correlation_id]] = "", "", _xlfn.XLOOKUP(Table14[[#This Row],[correlation_id]], 'ITAP Ref'!A:A, 'ITAP Ref'!C:C, "")) -> GRANITE | Q71: FiberJackAddRebuildService
A72: bb0063 | B72: Add | C72: Mass Markets | D72: Field | E72: Broadband | F72: 2 | G72: Onboard & Activate | H72: 5 | I72: Setup & Activate | J72: 1 | K72: Install Consumer Broadband | L72: 16 | N72: Check Port | O72: 9723 | P72: =IF(Table14[[#This Row],[correlation_id]] = "", "", _xlfn.XLOOKUP(Table14[[#This Row],[correlation_id]], 'ITAP Ref'!A:A, 'ITAP Ref'!C:C, "")) -> GRANITE | Q72: deleteFiberJack | R72: 45923
A73: bb0063 | B73: Add | C73: Mass Markets | D73: Field | E73: Broadband | F73: 2 | G73: Onboard & Activate | H73: 5 | I73: Setup & Activate | J73: 1 | K73: Install Consumer Broadband | L73: 21 | N73: Install Buried Drop Request | O73: 32007 | P73: =IF(Table14[[#This Row],[correlation_id]] = "", "", _xlfn.XLOOKUP(Table14[[#This Row],[correlation_id]], 'ITAP Ref'!A:A, 'ITAP Ref'!C:C, "")) -> ABWS-D | Q73: createAbwsTicket | R73: 45929
A74: bb0063 | B74: Add | C74: Mass Markets | D74: Field | E74: Broadband | F74: 2 | G74: Onboard & Activate | H74: 5 | I74: Setup & Activate | J74: 1 | K74: Install Consumer Broadband | L74: 22 | N74: Register RG | O74: 16188 | P74: =IF(Table14[[#This Row],[correlation_id]] = "", "", _xlfn.XLOOKUP(Table14[[#This Row],[correlation_id]], 'ITAP Ref'!A:A, 'ITAP Ref'!C:C, "")) -> BBNMS-LS | Q74: BBNMSSendNADSwapCompletion
A75: bb0063 | B75: Add | C75: Mass Markets | D75: Field | E75: Broadband | F75: 2 | G75: Onboard & Activate | H75: 5 | I75: Setup & Activate | J75: 1 | K75: Install Consumer Broadband | L75: 22 | N75: Register RG | O75: 10593 | P75: =IF(Table14[[#This Row],[correlation_id]] = "", "", _xlfn.XLOOKUP(Table14[[#This Row],[correlation_id]], 'ITAP Ref'!A:A, 'ITAP Ref'!C:C, "")) -> ISAAC WFE | Q75: BBNMSSendNADSwapCompletion | R75: 45924
A76: bb0063 | B76: Add | C76: Mass Markets | D76: Field | E76: Broadband | F76: 2 | G76: Onboard & Activate | H76: 5 | I76: Setup & Activate | J76: 1 | K76: Install Consumer Broadband | L76: 16 | N76: Check Port | O76: 16188 | P76: =IF(Table14[[#This Row],[correlation_id]] = "", "", _xlfn.XLOOKUP(Table14[[#This Row],[correlation_id]], 'ITAP Ref'!A:A, 'ITAP Ref'!C:C, "")) -> BBNMS-LS | Q76: BBNMSRetrieveUnlockPort
A77: bb0063 | B77: Add | C77: Mass Markets | D77: Field | E77: Broadband | F77: 2 | G77: Onboard & Activate | H77: 5 | I77: Setup & Activate | J77: 1 | K77: Install Consumer Broadband | L77: 16 | N77: Check Port | O77: 16188 | P77: =IF(Table14[[#This Row],[correlation_id]] = "", "", _xlfn.XLOOKUP(Table14[[#This Row],[correlation_id]], 'ITAP Ref'!A:A, 'ITAP Ref'!C:C, "")) -> BBNMS-LS | Q77: BBNMSRetrieveNADInfo
A78: bb0063 | B78: Add | C78: Mass Markets | D78: Care | E78: Broadband | F78: 4 | G78: Service & Support | H78: 1 | I78: Report Issue | J78: 1 | K78: CallBack ATTGuarantee | L78: 5 | N78: Make Call Back | O78: 21359 | P78: =IF(Table14[[#This Row],[correlation_id]] = "", "", _xlfn.XLOOKUP(Table14[[#This Row],[correlation_id]], 'ITAP Ref'!A:A, 'ITAP Ref'!C:C, "")) -> ATT CCTP MC VHT FRAME | Q78: UpdateVhtUserData
A79: bb0063 | B79: Add | C79: Mass Markets | D79: Care | E79: Broadband | F79: 4 | G79: Service & Support | H79: 1 | I79: Report Issue | J79: 1 | K79: CallBack ATTGuarantee | L79: 5 | N79: Make Call Back | O79: 21359 | P79: =IF(Table14[[#This Row],[correlation_id]] = "", "", _xlfn.XLOOKUP(Table14[[#This Row],[correlation_id]], 'ITAP Ref'!A:A, 'ITAP Ref'!C:C, "")) -> ATT CCTP MC VHT FRAME | Q79: UpdateVhtSingleCtiUserData
A80: bb0063 | B80: Add | C80: Mass Markets | D80: Care | E80: Broadband | F80: 4 | G80: Service & Support | H80: 1 | I80: Report Issue | J80: 1 | K80: CallBack ATTGuarantee | L80: 5 | M80: ATT CCTP NMC VHT FRAME->> ATT CCTP ICM GEN ADAPTER FRAME: UpdateVhtSingleCtiUserData ATT CCTP NMC VHT FRAME->> ATT CCTP ICM GEN ADAPTER FRAME: UpdateVHTGenesysUserData ATT CCTP NMC VHT FRAME->> ATT CCTP NMC VHT FRAME:UpdateVhtUserData | N80: Make Call Back | O80: 21359 | P80: =IF(Table14[[#This Row],[correlation_id]] = "", "", _xlfn.XLOOKUP(Table14[[#This Row],[correlation_id]], 'ITAP Ref'!A:A, 'ITAP Ref'!C:C, "")) -> ATT CCTP MC VHT FRAME | Q80: UpdateVhtGenesysUserData
A81: bb0063 | B81: Add | C81: Mass Markets | D81: Care | E81: Broadband | F81: 4 | G81: Service & Support | H81: 1 | I81: Report Issue | J81: 1 | K81: CallBack ATTGuarantee | L81: 6 | M81: ATT CCTP NMC VHT FRAME->> ATT CCTP CTI FRAME: EgCtiRoute ATT CCTP NMC VHT FRAME->> ATT CCTP CTI FRAME: AssociateVhtInteraction ATT CCTP NMC VHT FRAME->> ATT CCTP CTI FRAME: AssocaiteVhtGenesysInteraction ATT CCTP NMC VHT FRAME->> ATT CCTP CTI FRAME: AssociateVhtSingleCtiInteraction | N81: Integrate Telephony | O81: 9367 | P81: =IF(Table14[[#This Row],[correlation_id]] = "", "", _xlfn.XLOOKUP(Table14[[#This Row],[correlation_id]], 'ITAP Ref'!A:A, 'ITAP Ref'!C:C, "")) -> ATT CCTP CTI FRAME | Q81: EgCtiRoute
A82: bb0063 | B82: Add | C82: Mass Markets | D82: Field | E82: Broadband | F82: 2 | G82: Onboard & Activate | H82: 5 | I82: Setup & Activate | J82: 1 | K82: Install Consumer Broadband | L82: 22 | N82: Register RG | O82: 16188 | P82: =IF(Table14[[#This Row],[correlation_id]] = "", "", _xlfn.XLOOKUP(Table14[[#This Row],[correlation_id]], 'ITAP Ref'!A:A, 'ITAP Ref'!C:C, "")) -> BBNMS-LS | Q82: BBNMSRetrieveNADInfo
A83: bb0063 | B83: Add | C83: Mass Markets | D83: Field | E83: Broadband | F83: 2 | G83: Onboard & Activate | H83: 5 | I83: Setup & Activate | J83: 1 | K83: Install Consumer Broadband | L83: 22 | N83: Register RG | O83: 10593 | P83: =IF(Table14[[#This Row],[correlation_id]] = "", "", _xlfn.XLOOKUP(Table14[[#This Row],[correlation_id]], 'ITAP Ref'!A:A, 'ITAP Ref'!C:C, "")) -> ISAAC WFE | Q83: BBNMSRetrieveNADInfo | R83: 45924
A84: tm0828 | B84: Add | C84: Mass Markets | D84: Online | E84: Mobility | F84: 1 | G84: Shop & Purchase | H84: 2 | I84: Order Plan/Device | J84: 1 | K84: Purchase Product | L84: 1 | M84: ATTCOM ->> IDPUpperFunnelCloud: idp-content-orchestration ATTCOM ->> IDPUpperFunnelCloud: recommendationms | N84: Go to att.com | O84: 31548 | P84: =IF(Table14[[#This Row],[correlation_id]] = "", "", _xlfn.XLOOKUP(Table14[[#This Row],[correlation_id]], 'ITAP Ref'!A:A, 'ITAP Ref'!C:C, "")) -> IDP-Upper Funnel Cloud | Q84: idp-content-orchestration
A85: bb0063 | B85: Add | C85: Corporate Systems | D85: Human Resources | E85: SOX | F85: 1 | G85: Onboard | H85: 5 | I85: Hiring Guidelines | J85: 1 | K85: Onboard New Hire to Payroll | L85: 5 | N85: Determine Calculation Group | O85: 29338 | P85: =IF(Table14[[#This Row],[correlation_id]] = "", "", _xlfn.XLOOKUP(Table14[[#This Row],[correlation_id]], 'ITAP Ref'!A:A, 'ITAP Ref'!C:C, "")) -> Workday | Q85: HCM-Link | R85: POG no API
A86: bb0063 | B86: Add | C86: Mass Markets | D86: Field | E86: Broadband | F86: 2 | G86: Onboard & Activate | H86: 5 | I86: Setup & Activate | J86: 1 | K86: Install Consumer Broadband | L86: 16 | N86: Check Port | O86: 16188 | P86: =IF(Table14[[#This Row],[correlation_id]] = "", "", _xlfn.XLOOKUP(Table14[[#This Row],[correlation_id]], 'ITAP Ref'!A:A, 'ITAP Ref'!C:C, "")) -> BBNMS-LS | Q86: BBNMSRetrieveLockPort
A87: bb0063 | B87: Add | C87: Mass Markets | D87: Field | E87: Broadband | F87: 2 | G87: Onboard & Activate | H87: 5 | I87: Setup & Activate | J87: 1 | K87: Install Consumer Broadband | L87: 22 | N87: Register RG | O87: 16188 | P87: =IF(Table14[[#This Row],[correlation_id]] = "", "", _xlfn.XLOOKUP(Table14[[#This Row],[correlation_id]], 'ITAP Ref'!A:A, 'ITAP Ref'!C:C, "")) -> BBNMS-LS | Q87: BBNMSInitiateNADSwap
A88: bb0063 | B88: Add | C88: Mass Markets | D88: Field | E88: Broadband | F88: 2 | G88: Onboard & Activate | H88: 5 | I88: Setup & Activate | J88: 1 | K88: Install Consumer Broadband | L88: 22 | N88: Register RG | O88: 10593 | P88: =IF(Table14[[#This Row],[correlation_id]] = "", "", _xlfn.XLOOKUP(Table14[[#This Row],[correlation_id]], 'ITAP Ref'!A:A, 'ITAP Ref'!C:C, "")) -> ISAAC WFE | Q88: BBNMSInitiateNADSwap | R88: 45924
A89: bb0063 | B89: Add | C89: Mass Markets | D89: Field | E89: Broadband | F89: 2 | G89: Onboard & Activate | H89: 5 | I89: Setup & Activate | J89: 1 | K89: Install Consumer Broadband | L89: 16 | N89: Check Port | O89: 16188 | P89: =IF(Table14[[#This Row],[correlation_id]] = "", "", _xlfn.XLOOKUP(Table14[[#This Row],[correlation_id]], 'ITAP Ref'!A:A, 'ITAP Ref'!C:C, "")) -> BBNMS-LS | Q89: BBNMSDiagPwpInitialAssessment
A90: bb0063 | B90: Add | C90: Mass Markets | D90: Field | E90: Broadband | F90: 2 | G90: Onboard & Activate | H90: 5 | I90: Setup & Activate | J90: 1 | K90: Install Consumer Broadband | L90: 3 | N90: Review Jobs | O90: 30754 | P90: =IF(Table14[[#This Row],[correlation_id]] = "", "", _xlfn.XLOOKUP(Table14[[#This Row],[correlation_id]], 'ITAP Ref'!A:A, 'ITAP Ref'!C:C, "")) -> DMP | Q90: /WorkOrderServices/updateWorkOrder | R90: 45951
A91: bb0063 | B91: Add | C91: Mass Markets | D91: Field | E91: Broadband | F91: 2 | G91: Onboard & Activate | H91: 5 | I91: Setup & Activate | J91: 1 | K91: Install Consumer Broadband | L91: 19 | N91: Test Wifi Quality / Speed | O91: 14311 | P91: =IF(Table14[[#This Row],[correlation_id]] = "", "", _xlfn.XLOOKUP(Table14[[#This Row],[correlation_id]], 'ITAP Ref'!A:A, 'ITAP Ref'!C:C, "")) -> LSBBT | Q91: /speedtest/SpeedTestXMLServlet | R91: 45922
A92: bb0063 | B92: Add | C92: Mass Markets | D92: Field | E92: Broadband | F92: 2 | G92: Onboard & Activate | H92: 5 | I92: Setup & Activate | J92: 1 | K92: Install Consumer Broadband | L92: 19 | N92: Test Wifi Quality / Speed | O92: 14311 | P92: =IF(Table14[[#This Row],[correlation_id]] = "", "", _xlfn.XLOOKUP(Table14[[#This Row],[correlation_id]], 'ITAP Ref'!A:A, 'ITAP Ref'!C:C, "")) -> LSBBT | Q92: /speedtest/SpeedTestXMLServlet | R92: 45924
A93: bb0063 | B93: Add | C93: Mass Markets | D93: Field | E93: Broadband | F93: 2 | G93: Onboard & Activate | H93: 5 | I93: Setup & Activate | J93: 1 | K93: Install Consumer Broadband | L93: 20 | N93: Check Realtime LPA | O93: 14311 | P93: =IF(Table14[[#This Row],[correlation_id]] = "", "", _xlfn.XLOOKUP(Table14[[#This Row],[correlation_id]], 'ITAP Ref'!A:A, 'ITAP Ref'!C:C, "")) -> LSBBT | Q93: /scanr/LoopCheckServlet | R93: 45922
A94: bb0063 | B94: Add | C94: Mass Markets | D94: Field | E94: Broadband | F94: 2 | G94: Onboard & Activate | H94: 5 | I94: Setup & Activate | J94: 1 | K94: Install Consumer Broadband | L94: 19 | N94: Test Wifi Quality / Speed | O94: 14311 | P94: =IF(Table14[[#This Row],[correlation_id]] = "", "", _xlfn.XLOOKUP(Table14[[#This Row],[correlation_id]], 'ITAP Ref'!A:A, 'ITAP Ref'!C:C, "")) -> LSBBT | Q94: /rgqualitycheck/RGQualityServlet | R94: 45922
A95: bb0063 | B95: Add | C95: Mass Markets | D95: Field | E95: Broadband | F95: 2 | G95: Onboard & Activate | H95: 5 | I95: Setup & Activate | J95: 1 | K95: Install Consumer Broadband | L95: 4 | N95: Select Job / View Comments | O95: 27267 | P95: =IF(Table14[[#This Row],[correlation_id]] = "", "", _xlfn.XLOOKUP(Table14[[#This Row],[correlation_id]], 'ITAP Ref'!A:A, 'ITAP Ref'!C:C, "")) -> (FED) - FASTBPM | Q95: /restservices/engine-rest/v1/engine/default/process-definition/key/UpdateWorkListService/start | R95: 45953
A96: bb0063 | B96: Add | C96: Mass Markets | D96: Field | E96: Broadband | F96: 2 | G96: Onboard & Activate | H96: 5 | I96: Setup & Activate | J96: 1 | K96: Install Consumer Broadband | L96: 6 | N96: Arrive on Prem / Update Job | O96: 27267 | P96: =IF(Table14[[#This Row],[correlation_id]] = "", "", _xlfn.XLOOKUP(Table14[[#This Row],[correlation_id]], 'ITAP Ref'!A:A, 'ITAP Ref'!C:C, "")) -> (FED) - FASTBPM | Q96: /restservices/engine-rest/v1/engine/default/process-definition/key/UpdateWorkListService/start | R96: 45953
A97: bb0063 | B97: Add | C97: Mass Markets | D97: Field | E97: Broadband | F97: 2 | G97: Onboard & Activate | H97: 5 | I97: Setup & Activate | J97: 1 | K97: Install Consumer Broadband | L97: 24 | M97: Atlas ->> FASTBPM: /restservices/engine-rest/v1/engine/default/process-definition/key/UpdateWorkListService/start FASTBPM ->> EDGE: UpdateDispatchWorkOrder | N97: Mark Job Complete | O97: 27267 | P97: =IF(Table14[[#This Row],[correlation_id]] = "", "", _xlfn.XLOOKUP(Table14[[#This Row],[correlation_id]], 'ITAP Ref'!A:A, 'ITAP Ref'!C:C, "")) -> (FED) - FASTBPM | Q97: /restservices/engine-rest/v1/engine/default/process-definition/key/UpdateWorkListService/start | R97: 45953
A98: bb0063 | B98: Add | C98: Mass Markets | D98: Field | E98: Broadband | F98: 2 | G98: Onboard & Activate | H98: 5 | I98: Setup & Activate | J98: 1 | K98: Install Consumer Broadband | L98: 3 | N98: Review Jobs | O98: 27267 | P98: =IF(Table14[[#This Row],[correlation_id]] = "", "", _xlfn.XLOOKUP(Table14[[#This Row],[correlation_id]], 'ITAP Ref'!A:A, 'ITAP Ref'!C:C, "")) -> (FED) - FASTBPM | Q98: /restservices/engine-rest/v1/engine/default/process-definition/key/InquireDispatchWorkOrderService/start | R98: 45953
A99: bb0063 | B99: Add | C99: Mass Markets | D99: Field | E99: Broadband | F99: 2 | G99: Onboard & Activate | H99: 5 | I99: Setup & Activate | J99: 1 | K99: Install Consumer Broadband | L99: 4 | N99: Select Job / View Comments | O99: 27267 | P99: =IF(Table14[[#This Row],[correlation_id]] = "", "", _xlfn.XLOOKUP(Table14[[#This Row],[correlation_id]], 'ITAP Ref'!A:A, 'ITAP Ref'!C:C, "")) -> (FED) - FASTBPM | Q99: /restservices/engine-rest/v1/engine/default/process-definition/key/InquireDispatchWorkOrderService/start | R99: 45953
A100: bb0063 | B100: Add | C100: Mass Markets | D100: Field | E100: Broadband | F100: 2 | G100: Onboard & Activate | H100: 5 | I100: Setup & Activate | J100: 1 | K100: Install Consumer Broadband | L100: 7 | N100: Review Order w/Customer | O100: 27267 | P100: =IF(Table14[[#This Row],[correlation_id]] = "", "", _xlfn.XLOOKUP(Table14[[#This Row],[correlation_id]], 'ITAP Ref'!A:A, 'ITAP Ref'!C:C, "")) -> (FED) - FASTBPM | Q100: /restservices/engine-rest/v1/engine/default/process-definition/key/InquireDispatchWorkOrderService/start | R100: 45953
...

Sheet ITAP Ref
A1: Correlation ID | B1: Name | C1: Application acronym | D1: Number | E1: Emergency tier | F1: Business criticality
A2: 100 | B2: Customer Enhanced System for Access Requests | C2: CESAR | D2: APM0008615 | E2: Mission critical | F2: Business Operational | H2: Updated pull 1/8/26
A3: 10010 | B3: Viking Enterprise Account Reconciliation Process (VK EARP) | C3: VK EARP | D3: APM0009082 | E3: Out of Scope | F3: Deferrable
A4: 10013 | B4: Quick Hits HLLAPI Output Generator (HOG) | C4: QH HOG | D4: APM0009083 | E4: Non critical | F4: Administrative
A5: 10027 | B5: TIRKS to Billing Reconciliation | C5: TTBR | D5: APM0009085 | E5: Out of Scope | F5: Administrative
A6: 10035 | B6: Oracle Directory Naming (aka ONames LDAP OUD OID) | C6: ODM | D6: APM0009086 | E6: Out of Scope | F6: Mission Critical
A7: 10038 | B7: Lightspeed Order Management System | C7: LS-OMS | D7: APM0009087 | E7: Mission critical | F7: Mission Critical
A8: 10053 | B8: VMware vCenter | C8: VMVC | D8: APM0009088 | E8: Mission critical | F8: Business Critical
A9: 10055 | B9: Enterprise Bill Message and Insert System | C9: EBMIS | D9: APM0009089 | E9: Non critical | F9: Business Operational
A10: 10056 | B10: Lightspeed CRM | C10: LS CRM | D10: APM0009090 | E10: Mission critical | F10: Mission Critical
A11: 10058 | B11: Got AMA | C11: gotama | D11: APM0009091 | E11: Non critical | F11: Administrative
A12: 10059 | B12: OPT E MAN provision tool | C12: OPT | D12: APM0009092 | E12: Non critical | F12: Administrative
A13: 10089 | B13: Customer Contact System - Tuxedo | C13: CCS-Tuxedo | D13: APM0009060 | E13: Non critical | F13: Business Operational
A14: 10090 | B14: TZSS Business Customized Application Solutions | C14: TZSS BCA | D14: APM0009061 | E14: Out of Scope | F14: Administrative
... A805: 16868 | B805: SN613 & SN613M | C805: SN613 & SN613M | D805: APM0015072 | E805: Non critical | F805: Deferrable
A806: 16874 | B806: Communications Data Group, Inc. Carrier Access Billing System | C806: CDG CABS | D806: APM0009888 | F806: Administrative
A807: 16878 | B807: CISCO-CTM-LNS | C807: CTM-LNS-CISCO | D807: APM0009889 | E807: Non critical | F807: Administrative
A808: 16880 | B808: IP Voice Configuration Manager | C808: IP-VCM | D808: APM0009890 | E808: Non critical | F808: Business Critical
A809: 16883 | B809: NESAC maintenance access and support of 4ESS network elements | C809: NESAC | D809: APM0009891 | E809: Non critical | F809: Deferrable
A810: 16887 | B810: ESCAPE RAM Web Worklist | C810: ESCAPE RAM Web worklist | D810: APM0009892 | E810: Non critical | F810: Administrative
A811: 16890 | B811: IP Solution Center | C811: ISC | D811: APM0009893 | E811: Out of Scope | F811: Administrative
A812: 16891 | B812: Technical Space Operations Intranet | C812: DCSWEB | D812: APM0015886 | E812: Non critical | F812: Deferrable
A813: 16894 | B813: Orbix z/OS(Mainframe) | C813: Orbix z/OS | D813: APM0009872 | E813: Non critical | F813: Business Operational
A814: 16895 | B814: Shared Hosting MQ Infrastructure | C814: SHMQI | D814: APM0009873 | E814: Non critical | F814: Business Critical
A815: 16907 | B815: Layer3 Access servers | C815: OV ASI | D815: APM0009875 | E815: Out of Scope | F815: Administrative
A816: 16909 | B816: ITO DCS Projects | C816: ITODCS | D816: APM0009877 | E816: Out of Scope | F816: Deferrable
A817: 16993 | B817: AFT Discovery | C817: AFT-Discovery | D817: APM0009878 | E817: Non critical | F817: Administrative
A818: 16994 | B818: Converged AT&T Network Operations Provisioning & Inventory | C818: CANOPI | D818: APM0009879 | E818: Mission critical | F818: Business Critical
... A868: 17384 | B868: Cisco CEMF/SCM | C868: Cisco CEMF/SCM | D868: APM0009934 | E868: Out of Scope | F868: Administrative
A869: 17397 | B869: Fraud Tools and Metrics | C869: FraudMetrics | D869: APM0015902 | F869: Deferrable
A870: 17411 | B870: Control-Plane Monitoring | C870: PMOSS_Routing-Mon | D870: APM0014989 | E870: Non critical | F870: Business Operational
A871: 17425 | B871: CSO Website | C871: csowebsite | D871: APM0009936 | E871: Non critical | F871: Deferrable
A872: 17443 | B872: Global TACACS | C872: GTAC | D872: APM0009937 | E872: Mission critical | F872: Business Critical
A873: 17447 | B873: ITO - HP Project and Portfolio Management Center | C873: ITO-HPPPM | D873: APM0009938 | E873: Non critical | F873: Administrative
A874: 17455 | B874: Customer Rules Feedback Tool | C874: CRFT | D874: APM0009939 | E874: Out of Scope | F874: Deferrable
A875: 17456 | B875: Ciena Historical Statistics Collection | C875: Ciena HSC | D875: APM0009940 | F875: Deferrable
A876: 17483 | B876: ETL OPERATIONS | C876: ETL OPS | D876: APM0009943 | E876: Non critical | F876: Administrative
A877: 17484 | B877: E911 External File Server | C877: E911-EFS | D877: APM0009944 | E877: Mission critical | F877: Mission Critical
A878: 17486 | B878: CRE Temp ID | C878: TempID | D878: APM0015477 | E878: Out of Scope | F878: Deferrable
A879: 17488 | B879: CFEngine | C879: CFE | D879: APM0009987 | E879: Non critical | F879: Non-Essential
A880: 17555 | B880: Ordering, Care & Billing | C880: OrdCare&Bill | D880: APM0015054 | E880: Out of Scope | F880: Deferrable
A881: 17560 | B881: INTEGRATED SYSTEMS BILLER - WEB SUPPORT | C881: GMPISBWEB | D881: APM0009993 | E881: Out of Scope | F881: Business Operational
A882: 17574 | B882: GBBSO - WebView | C882: GBBSO - WebView | D882: APM0009995 | E882: Non critical | F882: Administrative
A883: 17576 | B883: GBBSO - Worklist Manager | C883: GBBSO - Worklist | D883: APM0015135 | E883: Non critical | F883: Non-Essential
A884: 17582 | B884: Financial Systems Data archive | C884: FSDA | D884: APM0009945 | E884: Non critical | F884: Administrative
A885: 17583 | B885: Telegence - Dealer | C885: TLGDLR | D885: APM0009946 | E885: Non critical | F885: Business Critical
A886: 17595 | B886: DocHarbor Optical System | C886: Optical | D886: APM0009948 | E886: Non critical | F886: Administrative
A887: 17599 | B887: Billing Excellence Superior Technology | C887: BEST | D887: APM0009949 | E887: Mission critical | F887: Business Critical
... A912: 17765 | B912: Common Product Catalog | C912: CPC | D912: APM0009985 | E912: Mission critical | F912: Mission Critical
A913: 17767 | B913: Partner Automated On-boarding System | C913: PAOS | D913: APM0015636 | F913: Business Operational
A914: 17784 | B914: Geographic Eligibility and Reference Service | C914: GEARS | D914: APM0009996 | E914: Mission critical | F914: Mission Critical
A915: 17786 | B915: Redhat Network Satellite | C915: RHNSAT | D915: APM0009997 | E915: Out of Scope | F915: Administrative
A916: 17787 | B916: Tivoli Netcool/Omnibus | C916: Netcool-ITO | D916: APM0009998 | E916: Mission critical | F916: Business Critical
A917: 17790 | B917: Express Station, Welcome Center (rsIQ), Kioware | C917: ES, rsIQ, Kioware, Kiosk, ES2 | D917: APM0015267 | E917: Mission critical | F917: Mission Critical
A918: 17803 | B918: NBI Number Agent | C918: NNA | D918: APM0010149 | E918: Mission critical | F918: Mission Critical
A919: 17805 | B919: Dealer Workspace | C919: DWS | D919: APM0010150 | E919: Non critical | F919: Business Operational
A920: 17813 | B920: Microsoft System Center Operations Manager | C920: MS SCOM | D920: APM0009999 | E920: Out of Scope | F920: Non-Essential
A921: 17815 | B921: Accounting Subledger Processing Engine | C921: ASPEN | D921: APM0010000 | E921: Non critical | F921: Business Critical
A922: 17852 | B922: Microsoft Forefront Identity Manager 2010 R2 | C922: MIM | D922: APM0010003 | E922: Non critical | F922: Business Operational
A923: 17855 | B923: Quest Recovery Manager for Active Directory | C923: RMAD | D923: APM0010004 | E923: Out of Scope | F923: Non-Essential
A924: 17873 | B924: Mass Data Entry 4.0 | C924: MDE 4.0, MDE, Mass Data Entry | D924: APM0010006 | E924: Non critical | F924: Business Critical
A925: 17876 | B925: Mediation Data | C925: MEDD | D925: APM0010007 | E925: Mission critical | F925: Business Critical
... A1107: 19363 | B1107: Credit and Collections Analytics and Reporting | C1107: CCAR | D1107: APM0014904 | E1107: Non critical | F1107: Administrative
A1108: 19368 | B1108: LS-Certificate Authority | C1108: LS-CA for STB | D1108: APM0010257 | F1108: Business Critical
A1109: 19375 | B1109: OVALS Geolocation Information System | C1109: OVALS GIS | D1109: APM0010260 | E1109: Mission critical | F1109: Business Critical
A1110: 19377 | B1110: Automated System Recovery Manual | C1110: AutoSRM | D1110: APM0010261 | E1110: Non critical | F1110: Administrative
A1111: 19399 | B1111: Electronic Rapid Deployment 2nd Generation | C1111: eRD 2G | D1111: APM0010263 | E1111: Non critical | F1111: Administrative
A1112: 19402 | B1112: Ciena ESM (Ethernet Services Manager) | C1112: Ciena ESM | D1112: APM0010264 | E1112: Out of Scope | F1112: Business Operational
A1113: 19404 | B1113: Toll Data | C1113: TD - DW | D1113: APM0014962 | E1113: Out of Scope | F1113: Deferrable
A1114: 19409 | B1114: Access Order Specification Tracking Environment | C1114: AOSTE | D1114: APM0010267 | E1114: Non critical | F1114: Administrative
A1115: 19410 | B1115: CCT ATT CCTP HISTORICAL REPORTING FRAMEWORK | C1115: ATT CCTP HISTORICAL REPORTING FRAME | D1115: APM0014857 | E1115: Out of Scope | F1115: Administrative
A1116: 19432 | B1116: Workflow Operations Center (WOC) Data Team | C1116: WOCDT | D1116: APM0010268 | E1116: Non critical | F1116: Administrative
A1117: 19439 | B1117: FIRST-Acquire Study Solve Execute & Track | C1117: FIRST-ASSET | D1117: APM0010269 | E1117: Mission critical | F1117: Business Critical
A1118: 19440 | B1118: Disaster Recovery Database | C1118: DRDB | D1118: APM0010270 | E1118: Non critical | F1118: Deferrable
A1119: 19454 | B1119: LUCENT-NAVIS-OPTICAL-EMS | C1119: WAVESTAR-OC48 | D1119: APM0010271 | E1119: Out of Scope | F1119: Non-Essential
A1120: 19457 | B1120: CFAS Oracle Internet Expenses | C1120: CFAS-OIE | D1120: APM0015465 | E1120: Out of Scope | F1120: Deferrable
... A1136: 19553 | B1136: NEC-EMS-100-ADM | C1136: NEC-EMS-100-ADM | D1136: APM0010293 | E1136: Out of Scope | F1136: Administrative
A1137: 19574 | B1137: Credit and Collection Tools | C1137: CC Tools | D1137: APM0010295 | F1137: Non-Essential
A1138: 19575 | B1138: OpenText eDocs DM | C1138: Legal eDocs | D1138: APM0010296 | E1138: Out of Scope | F1138: Business Operational
A1139: 19578 | B1139: SOE Workflow Automation Tool | C1139: SOE WAT | D1139: APM0010298 | E1139: Non critical | F1139: Business Operational
A1140: 19592 | B1140: Jenkins | C1140: Jenkins | D1140: APM0010300 | E1140: Non critical | F1140: Business Critical
A1141: 19617 | B1141: TIVOLI DECISION SUPPORT FOR Z/OS (TDSZ) | C1141: TDSZ | D1141: APM0010302 | E1141: Out of Scope | F1141: Deferrable
A1142: 19623 | B1142: MPS LDAP | C1142: MPS-LDAP | D1142: APM0010340 | E1142: Mission critical | F1142: Business Critical
A1143: 19624 | B1143: CIENA-IOS-EMS | C1143: CIENA-ON-CENTER-EMS | D1143: APM0010341 | E1143: Out of Scope | F1143: Deferrable
A1144: 19625 | B1144: FUJITSU-NETSMART-EMS | C1144: NS1500-EMS | D1144: APM0010342 | E1144: Non critical | F1144: Non-Essential
A1145: 19648 | B1145: CFAS - Independent Callable Editor | C1145: CFAS-ICE | D1145: APM0015464 | E1145: Out of Scope | F1145: Deferrable
A1146: 19651 | B1146: CNS Notification Engine | C1146: CNOTE | D1146: APM0010343 | E1146: Out of Scope | F1146: Deferrable
A1147: 19668 | B1147: CRE IAC IVR | C1147: CREIVR | D1147: APM0015478 | E1147: Out of Scope | F1147: Business Operational
A1148: 1968 | B1148: TIRKS Interface Development & Support | C1148: TIRKS I/F Dev & Sup | D1148: APM0014710 | E1148: Mission critical | F1148: Business Critical
A1149: 19681 | B1149: Managed Automation Services | C1149: MAS | D1149: APM0010304 | E1149: Out of Scope | F1149: Non-Essential
... A1209: 19945 | B1209: WSH-T3 Admin | C1209: WSH-T3 JS | D1209: APM0010368 | E1209: Out of Scope | F1209: Non-Essential
A1210: 19953 | B1210: Restricted Party Listing (RPL) Screening Tool | C1210: MDRPS | D1210: APM0010369 | F1210: Deferrable
A1211: 19955 | B1211: CPNI Synchronizer | C1211: CPSYNC | D1211: APM0010370 | E1211: Non critical | F1211: Administrative
A1212: 19958 | B1212: Services Tracking And Reporting Gateway for Accessing Telecom Environments | C1212: Stargate | D1212: APM0010371 | E1212: Non critical | F1212: Administrative
A1213: 19961 | B1213: Retail Real Estate (RRE) Workflow | C1213: RRE Workflow | D1213: APM0010372 | E1213: Non critical | F1213: Deferrable
A1214: 19964 | B1214: Numeritrack Wireline | C1214: NuTWLN | D1214: APM0010373 | E1214: Mission critical | F1214: Business Critical
A1215: 19981 | B1215: Manitou | C1215: Mant | D1215: APM0010376 | E1215: Out of Scope | F1215: Deferrable
A1216: 19982 | B1216: STC Live (Spirent Test Center Live) | C1216: STCL | D1216: APM0010377 | E1216: Mission critical | F1216: Business Critical
A1217: 19984 | B1217: International Settlements, Trading and Routing System | C1217: iSTARS | D1217: APM0010378 | E1217: Non critical | F1217: Business Operational
A1218: 19986 | B1218: NORTEL-OMEA-EMS | C1218: OMEA-EMS-NORTEL | D1218: APM0010379 | E1218: Out of Scope | F1218: Deferrable
...

Sheet Pivot
N1: All Applications
A2: application | D2: api | E2: (blank) | N2: EDF
N3: AERO
A4: Row Labels | B4: Count of application | D4: Row Labels | E4: Count of application | N4: EXMGR
A5: Care | B5: 975 | D5: Care | E5: 225 | G5: =(GETPIVOTDATA("application",$A$4,"channel","Care")-GETPIVOTDATA("application",$D$4,"channel","Care"))/GETPIVOTDATA("application",$A$4,"channel","Care") -> 0.76923077 | I5: 0.73026316 | N5: EDGE
A6: Field | B6: 206 | D6: Field | E6: 55 | G6: =(GETPIVOTDATA("application",$A$4,"channel","Field")-GETPIVOTDATA("application",$D$4,"channel","Field"))/GETPIVOTDATA("application",$A$4,"channel","Field") -> 0.73300971 | I6: 0.79550102 | N6: EFMS
A7: Human Resources | B7: 15 | D7: Human Resources | E7: 11 | G7: =(GETPIVOTDATA("application",$A$4,"channel","Human Resources")-GETPIVOTDATA("application",$D$4,"channel","Human Resources"))/GETPIVOTDATA("application",$A$4,"channel","Human Resources") -> 0.26666667 | I7: 0.26666667 | N7: FORCE-DCOE
A8: MVNO | B8: 136 | D8: MVNO | E8: 46 | G8: =(GETPIVOTDATA("application",$A$4,"channel","MVNO")-GETPIVOTDATA("application",$D$4,"channel","MVNO"))/GETPIVOTDATA("application",$A$4,"channel","MVNO") -> 0.66176471 | I8: 0.22068966 | N8: GRETA
A9: Online | B9: 252 | D9: Online | E9: 118 | G9: =(GETPIVOTDATA("application",$A$4,"channel","Online")-GETPIVOTDATA("application",$D$4,"channel","Online"))/GETPIVOTDATA("application",$A$4,"channel","Online") -> 0.53174603 | I9: 0.76190476 | N9: GRID-AC
A10: Retail | B10: 858 | D10: Retail | E10: 98 | G10: =(GETPIVOTDATA("application",$A$4,"channel","Retail")-GETPIVOTDATA("application",$D$4,"channel","Retail"))/GETPIVOTDATA("application",$A$4,"channel","Retail") -> 0.88578089 | I10: 0.83189122 | N10: INSTAR
A11: (blank) | B11: 4 | D11: (blank) | E11: 4 | N11: OCX
A12: Business Field Services | B12: 17 | D12: Business Field Services | E12: 17 | N12: (FED) - OCX
A13: Global Enterprise Sales | B13: 57 | D13: Global Enterprise Sales | E13: 57 | N13: (FED) - OMX
A14: Service Assurance | B14: 55 | D14: Service Assurance | E14: 55 | N14: USRP
A15: Service Delivery | B15: 111 | D15: Service Delivery | E15: 111 | N15: WFA/C
A16: Grand Total | B16: 2686 | D16: Grand Total | E16: 797 | N16: R3:SG
N17: ACMS
N18: SOTS
N19: IDP Web-Support
N20: ATTMO
N21: HVD-VDI
N22: Sonus TCCS
N23: ECO USP
N24: ATT CCT AEP
N25: ATT CCT APIGEE
N26: ATT CCT Service Access Gateway
N27: CCT ATT IPCS
N28: DialogFlow
... N258: ATTCOMM

Sheet Mapping Legend
A1: E2EUX/STATUS Data Model
A2: J-Loader data elements dictionary
A3: Label/Data Element | B3: Description | C3: Notes
A4: editor | B4: Authorized user credentials of individual granted permissions to add/edit/delete
A5: action | B5: Data action: Add, Edit, Delete
A6: lineOfBusiness | B6: Enterprise business unit: Mass Markets, AT&T Business, Corporate Systems
A7: channel | B7: Service delivery function within Line of Business, see Reference Data tab
A8: product | B8: Business unit products aligned to E2EUX, see Reference Data tab
A9: domain_sequence | B9: Numeric value to identify domain order
A10: domain | B10: E2EUX Hiearchy, line of business specific: Lifecycle of the end-to-end customer journey
A11: sub_domain_sequence | B11: Numeric value to identify sub-domain order
A12: subdomain | B12: E2EUX Hiearchy, lifecycle segments within a specific journey domain
A13: business_flow_sequence | B13: Numeric value to identify business flow order | C13: This field will determine the order in which business flows are listed.
A14: business_flow | B14: End to end business process or customer journey
A15: e2eux_sequence | B15: Numeric value to identify E2EUX order | C15: This field will determine the order in which E2EUXes are listed
A16: sequence_uml
A17: e2eux | B17: An E-Tux is the list of repeatable tasks, and their respective technical capabilities used to quantify and measure experience
A18: correlation_id | B18: iTAP application indicator
A19: application | B19: System(s) supporting the E2EUX
A20: api | B20: Application interface(s) enabling systems supporting an E2EUX
A21: Date Updated | B21: Date API data was added to Service Now

Sheet Reference Data
A2: CHANNELS | E2: Mass Markets Journey Model
A3: Corporate Systems | B3: AT&T Business | C3: Mass Markets | E3: MM Channels | F3: MM Products | G3: D Seq | H3: MM Domains | I3: SD Seq | J3: MM Subdomains2
A4: Human Resources | B4: Customer Sales & Support | C4: Field | E4: Field | F4: Mobility | G4: 1 | H4: Shop & Purchase | I4: 1 | J4: Learn & Discover
A5: Finance | B5: Business Field Services | C5: Care | E5: Care | F5: Broadband | I5: 2 | J5: Order Plan/Device
A6: Supply Chain | B6: Customer Advocacy | C6: Retail | E6: Retail | F6: Wholesale Mobility | I6: 3 | J6: Order Addtional Products/Services
B7: Service Assurance | C7: MVNO | E7: MVNO | F7: AIA | I7: 4 | J7: Build Cart
B8: Service Delivery | C8: Online | E8: Online | F8: OneConnect | I8: 5 | J8: Checkout
B9: Global Enterprise Sales | G9: 2 | H9: Onboard & Activate | I9: 1 | J9: Receive Products
B10: Mid-Market Sales | I10: 2 | J10: Unbox Products
B11: Public Sector Sales | I11: 3 | J11: Setup & Activate
B12: Partner Solutions | I12: 4 | J12: Configure Settings & Preferences
B13: International Ecosystem Solutions | G13: 3 | H13: Use & Manage | I13: 1 | J13: Change Settings & Prefrences
B14: Digital Experience | I14: 2 | J14: Change Plan / Change Speed
I15: 3 | J15: Change Feature
A16: PRODUCTS | I16: 4 | J16: Upgrade Device / Equipment
A17: Corporate Systems | B17: Business | C17: Mass Markets | I17: 5 | J17: Order Additional Service
A18: SOX | B18: ABF | C18: Mobility | I18: 6 | J18: Upgrade Roles & Responsibilities
B19: ADI | C19: Wholesale Mobility | G19: 4 | H19: Service & Support | I19: 1 | J19: Report Issue
B20: ASE | C20: Broadband | I20: 2 | J20: Troubleshoot Issue
B21: ASEoD | C21: AIA | I21: 3 | J21: Resolve Issue
B22: IoT with AWB | C22: OneConnect | I22: 4 | J22: Confirm Resolution
B23: Mobility with AWB | I23: 5 | J23: Return Equipment
B24: ADD | G24: 5 | H24: Close & Separate | I24: 1 | J24: Close Account
B25: CRU | I25: 2 | J25: Return Equipment
B26: HSIA
B27: OAH | E27: Business Journey Model
B28: HSIA-E | E28: Business Channels | F28: Business Products | G28: D Seq | H28: Business Domains | I28: SD Seq | J28: Business Subdomains3
E29: Business Care and Sales | F29: ABF | G29: 1 | H29: Learn | I29: 1 | J29: Marketing Managment
A30: DOMAINS | E30: Business Field Services | F30: ADI | I30: 2 | J30: Advertising Management
A31: Corporate Systems | B31: Business | C31: Mass Markets | E31: Customer Advocacy | F31: ASE | I31: 3 | J31: Sales Account Management
A32: Onboard | B32: Learn | C32: Shop & Purchase | E32: Service Assurance | F32: ASEoD | I32: 4 | J32: Sales Activity Management
A33: Manage | B33: Buy | C33: Onboard & Activate | E33: Service Delivery | F33: IoT with AWB | I33: 5 | J33: Campaign Managment
A34: Support | B34: Get | C34: Use & Manage | F34: Mobility with AWB | I34: 6 | J34: Lead Managment
A35: Develop | B35: Use | C35: Service & Support | F35: ADD | I35: 7 | J35: Sales Opportunity Management
A36: Pay | B36: Pay | C36: Close & Separate | E36: Global Enterprise Sales | F36: CRU | I36: 8 | J36: Discovery Management
A37: Separate | B37: Separate | E37: Mid-Market Sales | F37: HSIA | I37: 9 | J37: Qualification Management
A38: Financial Management Approach | E38: Public Sector Sales | F38: OAH | G38: 2 | H38: Buy | I38: 1 | J38: Credit Check Management
A39: Manage Financial Resources | E39: Partner Solutions | F39: HSIA-E | I39: 2 | J39: Contract Management
A40: Manage Treasury | E40: International Ecosystem Solutions | I40: 3 | J40: Sales Order Management
A41: Perform Regulatory & Tax Accounting | I41: 4 | J41: Design Management
A42: Report Financial Results | I42: 5 | J42: Pricing Management
A43: Fulfillment | E43: Digital Experience | I43: 6 | J43: Proposal Management
A44: Logistics | G44: 3 | H44: Get | I44: 1 | J44: Order Management
A45: Procurement | I45: 2 | J45: Provisioning Management
A46: Policies | G46: 4 | H46: Use | I46: 1 | J46: Access & Security Management
A47: Strategic Planning | I47: 2 | J47: Dashboard Management
A48: Warehouse Management | I48: 3 | J48: Training & Tutorials Management
A49: Support Production | G49: 5 | H49: Pay | I49: 1 | J49: Account Pricing Management
I50: 2 | J50: Billing Comms Management
A51: SUBDOMAINS | I51: 3 | J51: Bill Event Error Management
A52: Corporate Systems | B52: Business | C52: Mass Markets | I52: 4 | J52: Billing Management
A53: Define Requirements | B53: Marketing Managment | C53: Learn & Discover | I53: 5 | J53: Commit & Perform Management
A54: Create Workforce Strategy | B54: Advertising Management | C54: Order Plan/Device | I54: 6 | J54: Post Bill Management
A55: Competency Modeling | B55: Sales Account Management | C55: Order Addtional Products/Services | I55: 7 | J55: Invoice Arrange Management
A56: Employee Recruitment | B56: Sales Activity Management | C56: Build Cart | I56: 8 | J56: Payment Management
A57: Hiring Guidelines | B57: Campaign Managment | C57: Checkout | G57: 6 | H57: Support | I57: 1 | J57: Incident Management
A58: Terms of Employment | B58: Lead Managment | C58: Receive Products | I58: 2 | J58: Problem Management
A59: Code of Conduct | B59: Sales Opportunity Management | C59: Unbox Products | I59: 3 | J59: Event Management
A60: Manage Workforce Change | B60: Discovery Management | C60: Setup & Activate | I60: 4 | J60: Change Management
A61: Manage Employee & Labor Relations | B61: Qualification Management | C61: Configure Settings & Preferences | I61: 5 | J61: Diagnose Management
A62: Work Design | B62: Credit Check Management | C62: Change Settings & Prefrences
A63: Labor Contracts | B63: Contract Management | C63: Change Plan / Change Speed | E63: Corporate Systems Journey Model
A64: Union Contract Negotiation | B64: Sales Order Management | C64: Change Feature | E64: CS Channels | F64: CS Products | G64: D Seq | H64: CS Domains | I64: SD Seq | J64: CS Subdomains2
A65: Arbitration Management | B65: Design Management | C65: Upgrade Device / Equipment | E65: Human Resources | F65: SOX | G65: 1 | H65: Onboard | I65: 1 | J65: Define Requirements
A66: Performance Appraisal | B66: Pricing Management | C66: Order Additional Service | I66: 2 | J66: Create Workforce Strategy
A67: Counseling Programs | B67: Proposal Management | C67: Upgrade Roles & Responsibilities | I67: 3 | J67: Competency Modeling
A68: Employee Resource Groups | B68: Order Management | C68: Report Issue | I68: 4 | J68: Employee Recruitment
A69: Community & Charity Involvement | B69: Provisioning Management | C69: Troubleshoot Issue | I69: 5 | J69: Hiring Guidelines
A70: Occupational & Health Safety | B70: Access & Security Management | C70: Resolve Issue | I70: 6 | J70: Terms of Employment
A71: Equal Employment Opportunity | B71: Dashboard Management | C71: Confirm Resolution | I71: 7 | J71: Code of Conduct
A72: Employee Satisfaction Measurement & Management | B72: Training & Tutorials Management | C72: Return Equipment | G72: 2 | H72: Manage | I72: 1 | J72: Manage Workforce Change
A73: Strength Profiling | B73: Account Pricing Management | C73: Close Account | I73: 2 | J73: Manage Employee & Labor Relations
A74: Skills Assessment | B74: Billing Comms Management | C74: Return Equipment | I74: 3 | J74: Work Design
A75: Career Development | B75: Bill Event Error Management | I75: 4 | J75: Labor Contracts
A76: Renumeration Policies & Levels | B76: Billing Management | I76: 5 | J76: Union Contract Negotiation
A77: Allowance & Benefits | B77: Commit & Perform Management | I77: 6 | J77: Arbitration Management
A78: Compensation Guidelines | B78: Post Bill Management | I78: 7 | J78: Performance Appraisal
A79: Succession Planning | B79: Invoice Arrange Management | G79: 3 | H79: Support | I79: 1 | J79: Counseling Programs
A80: Termination Guidelines | B80: Payment Management | I80: 2 | J80: Employee Resource Groups
A81: Financial Management Scope & Objectives | B81: Incident Management | I81: 3 | J81: Community & Charity Involvement
A82: Determine Costing/ Budgeting Factors | B82: Problem Management | I82: 4 | J82: Occupational & Health Safety
A83: Define Financial Management Process | B83: Event Management | I83: 5 | J83: Equal Employment Opportunity
A84: Finalize Financial Management Approach | B84: Change Management | I84: 6 | J84: Employee Satisfaction Measurement & Management
A85: Develop Budgets | B85: Diagnose Management | G85: 4 | H85: Develop | I85: 1 | J85: Strength Profiling
A86: Allocate Financial Resources | I86: 2 | J86: Skills Assessment
A87: Design Capital Structure | I87: 3 | J87: Career Development
A88: Manage Financial Risk | G88: 5 | H88: Pay | I88: 1 | J88: Renumeration Policies & Levels
A89: Accounts Payable | I89: 2 | J89: Allowance & Benefits
A90: Payroll | I90: 3 | J90: Compensation Guidelines
A91: General Accounting | G91: 6 | H91: Separate | I91: 1 | J91: Succession Planning
A92: Inventory Transactions | I92: 2 | J92: Termination Guidelines
A93: Accounting for Fixed Assets | E93: Finance | G93: 1 | H93: Financial Management Approach | I93: 1 | J93: Financial Management Scope & Objectives
A94: Project Accounting | I94: 2 | J94: Determine Costing/ Budgeting Factors
A95: Finalize Accounts | I95: 3 | J95: Define Financial Management Process
A96: Manage Cash Flow | I96: 4 | J96: Finalize Financial Management Approach
A97: Forecast Financing Requirements | G97: 2 | H97: Manage Financial Resources | I97: 1 | J97: Develop Budgets
A98: Arrange Finance | I98: 2 | J98: Allocate Financial Resources
A99: Manage Short Term Investment | I99: 3 | J99: Design Capital Structure
A100: Make/Receive Foreign Exchange Payments | I100: 4 | J100: Manage Financial Risk
A101: Reconcile Bank & Financial Institution Statements | I101: 5 | J101: Accounts Payable
...

Sheet Dynatrace Apps
A1: MOTS ID | B1: Application Acronym | C1: Application Name | D1: Dynatrace Monitored
A2: 7983 | B2: #N/A | C2: Email Gateway System | D2: Y
A3: 14798 | C3: Security IDP | D3: Y
A4: 15945 | B4: Email-ODS | C4: Email Operational Data Store | D4: Y
A5: 17689 | B5: EDD | C5: Enterprise Document Delivery | D5: Y
A6: 17723 | B6: myAT&T Sales | C6: myAT&T Sales (MSa) | D6: Y
A7: 17766 | B7: CMS | C7: Content Management System | D7: Y
A8: 18185 | B8: OPSS | C8: Online Post Sales Support | D8: Y
A9: 18298 | B9: MyATT, MSe | C9: myAT&T Services (MSe) | D9: Y
A10: 21937 | B10: #N/A | C10: myAT&T Zone | D10: Y
A11: 23488 | B11: OCE | C11: DET Platform Online Order Capture Engine | D11: Y
A12: 24218 | B12: CMS | C12: Platform Content Management System | D12: Y
A13: 25145 | B13: Dynatrace | C13: DET Platform Dynatrace | D13: Y
A14: 25172 | B14: DET Search | C14: Legacy Search | D14: Y
A15: 26032 | B15: Upper Funnel | C15: Upper Funnel | D15: Y
A16: 27531 | B16: Digital IDP | C16: IDP - Integrated Digital Platform | D16: Y
A17: 27835 | B17: OMHUB | C17: Order Management Hub (Legacy) | D17: Y
A18: 28995 | B18: Order Graph | C18: Order Graph | D18: Y
A19: 29607 | B19: CPOP | C19: Centralized Products and Offers Platform | D19: Y
A20: 30519 | B20: IDP-Sales | C20: IDP-Sales | D20: Y
A21: 30547 | B21: IDP-Srv | C21: IDP-Services | D21: Y
A22: 30635 | B22: IDP-Support | C22: IDP-Support | D22: Y
A23: 30655 | C23: IDP-Platform | D23: Y
A24: 30656 | B24: IDP-Unlock | C24: IDP-Unlock | D24: Y
A25: 30657 | B25: CG | C25: IDP-Customer Graph | D25: Y
A26: 30686 | B26: CCMULE | C26: Customer Connect Salesforce Mulesoft | D26: Y
A27: 31202 | B27: IDP-TOBR | C27: IDP-TOBR | D27: Y
A28: 31467 | B28: IDP-Cloud | C28: IDP-Cloud | D28: Y
A29: 31468 | B29: CGC | C29: IDP-Customer Graph Cloud | D29: Y
A30: 31485 | B30: IDP-Personalization Cloud | C30: IDP-Personalization Cloud | D30: Y
A31: 31501 | B31: IDP- Adobe Personalization Cloud | C31: IDP- Adobe Personalization Cloud | D31: Y
A32: 31543 | B32: OG | C32: IDP-Order Graph Cloud | D32: Y
A33: 31548 | B33: IDP-Upper Funnel Cloud | C33: IDP-Upper Funnel Cloud | D33: Y
A34: 31565 | B34: IDP-PSC | C34: IDP-PSC | D34: Y
A35: 31881 | B35: IDP-Account Services Cloud | C35: IDP-Account Services Cloud | D35: Y
A36: 32166 | B36: IDP-OMHUB | C36: IDP-OMHUB | D36: Y
A37: 32286 | C37: IDP-Event Graph | D37: Y
A38: 32411 | C38: IDP-Sales Cloud | D38: Y
A39: 32470 | C39: IDP-Platform Cloud | D39: Y
A40: 32472 | C40: IDP-Cart Fulfillment Cloud | D40: Y
A41: 32560 | C41: P & O (CPOP/SPO) | D41: Y
A42: 32768 | C42: IDP-WebAcctMgmt | D42: Y

Sheet SvcNow
A1: MotsID | B1: Application | C1: Retail | D1: Care | E1: Field | F1: Online | G1: MVNx | H1: Corp Sys | I1: Ttrace | J1: TAPM | K1: Dynatrace | L1: SvcNow | M1: TAPM Status | N1: T-Trace Status | O1: Penchal Validated | P1: Status
A2: 23223 | B2: (FED) - AOTS | R2: Funded to Retire | S2: 2
A3: 23283 | B3: (FED) - COMS | I3: N | J3: Y | K3: N | M3: Onboarded | O3: Yet to configure in lightStep | P3: TAPM onboarded | R3: Not a candidate (tech stack) | S3: 16
A4: 27267 | B4: (FED) - FASTBPM | E4: X | I4: Y | J4: Y | K4: N | L4: Y | M4: Onboarded | N4: Prod in Progress | O4: configured in lightstep | P4: TAPM onboarded/partial T-Trace | R4: Not a candidate (third party) | S4: 11
A5: 24095 | B5: (FED) - GEARS | G5: X | I5: Y | J5: Y | K5: N | M5: Onboarded | N5: Fully Onboarded | O5: configured in lightstep | P5: TAPM & T-Trace onboarded | R5: Potential/needs review (3Q) | S5: 24
A6: 23439 | B6: (FED) - Interface CAS | C6: X | O6: configured in lightstep | R6: Push back from app team | S6: 2
A7: 23730 | B7: (FED) - TDICE | D7: X | I7: Y | J7: Y | K7: N | L7: Y | M7: Onboarded | N7: Prod in Progress | O7: configured in lightstep | P7: TAPM onboarded/partial T-Trace | R7: Retired | S7: 2
A8: 24433 | B8: (FED) - Unified Services | C8: X | D8: X | O8: configured in lightstep | R8: TAPM & T-Trace onboarded | S8: 15
A9: 23205 | B9: (FED)-CPC | C9: X | D9: X | I9: Y | J9: Y | K9: N | O9: configured in lightstep | R9: TAPM onboarded | S9: 27
A10: 10097 | B10: 5520 AMS | E10: X | I10: N | J10: N | K10: N | L10: N | M10: Potential Candidate | N10: 0 | O10: not available in lightstep | P10: Potential/needs review (3Q) | R10: TAPM Onboarded no traffic | S10: 1
A11: 30176 | B11: AA | D11: X | I11: N | J11: N | K11: N | L11: N | M11: Potential Candidate | N11: 0 | O11: not available in lightstep | P11: Potential/needs review (3Q) | R11: TAPM In Progress/T-Trace Onboarded | S11: 2
A12: 18781 | B12: ABPT | D12: X | E12: X | I12: Y | J12: Y | K12: N | L12: Y | M12: Onboarded | N12: 0 | O12: configured in lightstep | P12: TAPM onboarded | R12: TAPM onboarded / out of scope for T-Trace | S12: 1
A13: 32007 | B13: ABWS-D | E13: X | I13: Y | J13: Y | K13: N | L13: Y | M13: Onboarded | N13: 0 | O13: configured in lightstep | P13: TAPM onboarded | R13: TAPM onboarded/partial T-Trace | S13: 15
A14: 22827 | B14: Amp-MM - Invenio | D14: X | I14: N | J14: Y | K14: N | L14: N | M14: In Progress | N14: 0 | O14: not available in lightstep | P14: Potential/needs review (3Q) | R14: T-Stack Advanced (Dynatrace) | S14: 29
A15: 30420 | B15: Analytics Microservice | R15: T-Trace onboarded | S15: 8
A16: 28619 | B16: Atlas-UI | E16: X | I16: Y | J16: Y | K16: N | L16: Y | M16: Onboarded | N16: Fully Onboarded | O16: configured in lightstep | P16: TAPM & T-Trace onboarded | R16: Total | S16: =SUM(S2:S15) -> 155
A17: 26150 | B17: ATT CCT AEP | D17: X | I17: N | J17: N | K17: N | L17: N | M17: Not a candidate | N17: 0 | P17: Not a candidate (tech stack) | R17: Eligible | S17: 0.8
A18: 30793 | B18: ATT CCT APIGEE | D18: X | I18: N | J18: N | K18: N | L18: N | M18: Not a candidate | N18: 0 | P18: Not a candidate (Third party)
A19: 26215 | B19: ATT CCT Service Access Gateway | D19: X | I19: N | J19: N | K19: N | L19: N | M19: Potential Candidate | N19: 0 | O19: not available in lightstep | P19: Potential/needs review (3Q)
A20: 9367 | B20: ATT CCTP CTI FRAME | D20: X | I20: N | J20: N | K20: N | L20: N | M20: Blocked | N20: 0 | O20: not available in lightstep | P20: Push back from app team
A21: 20813 | B21: ATT CCTP ICM GEN ADAPTER FRAME | D21: X | I21: N | J21: Y | K21: N | L21: N | M21: UAT Complete | N21: 0 | P21: Not a candidate (Third party)
A22: 21359 | B22: ATT CCTP NMC VHT FRAME | D22: X | I22: N | J22: N | K22: N | L22: N | M22: Not a candidate | N22: 0 | P22: Not a candidate (Third party)
A23: 26959 | B23: ATT Coral Desktop | D23: X | I23: N | J23: Y | K23: N | L23: N | M23: In Progress | N23: 0 | O23: not available in lightstep | P23: Potential/needs review (3Q)
A24: 9248 | B24: ATT VERINT CQM | D24: X | I24: N | J24: N | K24: N | L24: N | M24: Not a candidate | N24: 0 | P24: Not a candidate (Third party)
A25: 25114 | B25: Avertack | C25: X | D25: X | I25: N | J25: Y | K25: N | L25: N | M25: In Progress | N25: Blocked | O25: configured in lightstep | P25: Push back from app team
A26: 19105 | B26: AVT | F26: X | I26: Y | J26: Y | K26: N | M26: Onboarded | N26: Fully Onboarded | O26: configured in lightstep | P26: TAPM & T-Trace onboarded
A27: 17215 | B27: BBNMS-CMI | E27: X | I27: N | J27: N | K27: N | L27: N | M27: Not a candidate | N27: 0 | P27: Not a candidate (tech stack)
A28: 16188 | B28: BBNMS-LS | E28: X | I28: Y | J28: N | K28: N | L28: Y | M28: Not a candidate | N28: Fully Onboarded | O28: configured in lightstep | P28: T-Trace onboarded
A29: 18372 | B29: BBNMS-SE | E29: X | I29: N | J29: N | K29: N | L29: N | M29: Not a candidate | N29: 0 | P29: Not a candidate (tech stack)
A30: 30687 | B30: BWSFMC | D30: X | I30: N | J30: N | K30: N | L30: N | M30: Not a candidate | N30: Potential Candidate | P30: Not a candidate (Third party)
A31: 71 | B31: CAMS | E31: X | I31: N | J31: N | K31: N | L31: N | M31: Potential Candidate | N31: 0 | O31: not available in lightstep | P31: Potential/needs review (3Q)
A32: 19867 | B32: CAP | F32: X | I32: N | J32: Y | K32: N | M32: Onboarded | N32: Blocked | O32: Yet to configure in lightStep | P32: TAPM onboarded
A33: 73 | B33: CAPM | C33: X | D33: X | I33: Y | J33: Y | K33: N | L33: Y | M33: Onboarded | N33: Fully Onboarded | O33: configured in lightstep | P33: TAPM & T-Trace onboarded
A34: 18224 | B34: CAS | C34: X | D34: X | I34: Y | J34: Y | K34: N | L34: Y | M34: Onboarded | N34: Prod in Progress | O34: configured in lightstep | P34: TAPM onboarded/partial T-Trace
A35: 33435 | B35: CAST | D35: X | I35: N | J35: N | K35: N | L35: N | M35: Potential Candidate | N35: 0 | O35: not available in lightstep | P35: Potential/needs review (3Q)
A36: 32255 | B36: CCDL | D36: X | I36: N | J36: N | K36: N | L36: N | M36: Potential Candidate | N36: 0 | O36: not available in lightstep | P36: Potential/needs review (3Q)
A37: 18293 | B37: CCM, Clarify, CM | D37: X | I37: N | J37: Y | K37: N | L37: N | M37: Onboarded | N37: 0 | O37: configured in lightstep | P37: TAPM onboarded
A38: 8841 | B38: MPSYS | C38: X | D38: X | F38: X | I38: Y | J38: Y | K38: Y | L38: Y | M38: Onboarded | N38: Fully Onboarded | O38: configured in lightstep | P38: TAPM & T-Trace onboarded
A39: 10038 | B39: LS-OMS | D39: X | E39: X | I39: N | J39: N | K39: Y | L39: N | M39: Not a candidate | N39: Blocked | P39: T-Stack Advanced (Dynatrace)
A40: 33687 | B40: CCMule-Sales | I40: N | J40: N | K40: N | M40: Not a candidate | P40: Not a candidate (tech stack)
A41: 33688 | B41: CCMule-Service | D41: X | I41: N | J41: N | K41: N | L41: N | M41: Not a candidate | N41: 0 | P41: Not a candidate (tech stack)
A42: 18678 | B42: CCPM | I42: N | J42: N | K42: N | M42: Potential Candidate | P42: Potential/needs review (3Q)
A43: 19166 | B43: CCR-Relational - CCR-R | D43: X | G43: X | I43: Y | J43: Y | K43: N | L43: Y | M43: Onboarded | N43: Prod in Progress | O43: configured in lightstep | P43: TAPM onboarded/partial T-Trace
A44: 17689 | B44: EDD | C44: X | I44: Y | J44: Y | K44: Y | L44: Y | M44: Onboarded | N44: Fully Onboarded | O44: configured in lightstep | P44: TAPM & T-Trace onboarded
A45: 25363 | B45: CCT ATT IPCS | D45: X | I45: N | J45: Y | K45: N | L45: N | M45: Started Onboarding | N45: 0 | P45: Potential/needs review (3Q)
A46: 30169 | B46: CEP | D46: X | I46: N | J46: N | K46: N | L46: N | M46: Not a candidate | N46: 0 | P46: Not a candidate (Third party)
A47: 23872 | B47: Chat | F47: X | I47: N | J47: N | K47: N | M47: Not a candidate | N47: Potential Candidate | P47: Potential/needs review (3Q)
A48: 17962 | B48: CP | I48: N | J48: Y | K48: N | M48: Onboarded | O48: not available in lightstep | P48: TAPM onboarded
A49: 17765 | B49: CPC | C49: X | D49: X | I49: Y | J49: Y | K49: N | L49: Y | M49: Onboarded | N49: Fully Onboarded | O49: configured in lightstep | P49: TAPM & T-Trace onboarded
A50: 22498 | B50: TDICE | D50: X | I50: N | J50: N | K50: Y | L50: N | M50: Not a candidate | N50: Potential Candidate | P50: T-Stack Advanced (Dynatrace)
A51: 19182 | B51: CS BOBPM | C51: X | I51: Y | J51: Y | K51: N | L51: Y | M51: Onboarded | N51: Prod in Progress | O51: configured in lightstep | P51: TAPM onboarded/partial T-Trace
A52: 19181 | B52: CS FOBPM | C52: X | F52: X | I52: Y | J52: Y | K52: N | O52: configured in lightstep
A53: 20181 | B53: CSI - Adapter | C53: X | I53: Y | J53: Y | K53: N | L53: Y | M53: Onboarded | N53: Prod in Progress | O53: configured in lightstep | P53: TAPM onboarded/partial T-Trace
A54: 20186 | B54: CSI - Credit and Val | D54: X | I54: Y | J54: Y | K54: N | M54: Onboarded | N54: Prod in Progress | O54: configured in lightstep | P54: TAPM onboarded/partial T-Trace
A55: 20182 | B55: CSI - Customer Care | C55: X | D55: X | G55: X | I55: Y | J55: Y | K55: N | L55: Y | M55: Onboarded | N55: Prod in Progress | O55: configured in lightstep | P55: TAPM onboarded/partial T-Trace
A56: 20188 | B56: CSI - Network Management | C56: X | F56: X | I56: Y | J56: Y | K56: N | L56: Y | M56: Onboarded | N56: Prod in Progress | O56: configured in lightstep | P56: TAPM onboarded/partial T-Trace
A57: 20187 | B57: CSI - Order and Subscription Mngt | C57: X | E57: X | I57: N | J57: Y | K57: N | L57: N | M57: Onboarded | N57: Prod in Progress | O57: configured in lightstep | P57: TAPM onboarded/partial T-Trace
A58: 20180 | B58: CSI - Product and Offer Mgt | F58: X | I58: Y | J58: Y | K58: N | M58: Onboarded | N58: Prod in Progress | O58: Yet to configure in lightStep | P58: TAPM onboarded/partial T-Trace
A59: 20184 | B59: CSI - Work Force | D59: X | I59: Y | J59: Y | K59: N | L59: Y | M59: Onboarded | N59: Prod in Progress | O59: configured in lightstep | P59: TAPM onboarded/partial T-Trace
A60: 17690 | B60: CSI Parent/Triage | C60: X | D60: X | G60: X | I60: N | J60: Y | K60: N | L60: N | M60: Onboarded | N60: Prod in Progress | O60: configured in lightstep | P60: TAPM onboarded/partial T-Trace
A61: 23901 | B61: CSI-CPSVC | I61: Y | J61: Y | K61: N | O61: configured in lightstep
A62: 30431 | B62: DAAS PLATFORM | D62: X | I62: N | J62: N | K62: N | L62: N | M62: Not a candidate | N62: Potential Candidate | P62: Retired
A63: 23488 | B63: OCE | F63: X | I63: N | J63: N | K63: Y | M63: Not a candidate | N63: Blocked | P63: T-Stack Advanced (Dynatrace)
A64: 31036 | B64: DialogFlow | D64: X | I64: N | J64: N | K64: N | L64: N | M64: Not a candidate | N64: 0 | P64: Not a candidate (Third party)
A65: 26965 | B65: SHM | D65: X | E65: X | I65: N | J65: N | K65: Y | L65: N | M65: Not a candidate | N65: Potential Candidate | P65: T-Stack Advanced (Dynatrace)
A66: 34322 | B66: Digital IDP-PCI-OMHub
A67: 30754 | B67: DMP | D67: X | E67: X | I67: Y | J67: Y | K67: N | L67: Y | M67: Onboarded | N67: Prod in Progress | O67: configured in lightstep | P67: TAPM onboarded/partial T-Trace
A68: 31479 | B68: DPG - Sales & Sunrise | D68: X | I68: N | J68: N | K68: N | L68: N | M68: Not a candidate | N68: 0 | P68: Not a candidate (tech stack)
A69: 4564 | B69: DSF | E69: X | I69: N | J69: N | K69: N | L69: N | M69: Not a candidate | N69: 0 | P69: Not a candidate (tech stack)
A70: 24809 | B70: DTV-ASMM | G70: X | I70: N | J70: N | K70: N | M70: Potential Candidate | P70: Potential/needs review (3Q)
A71: 18201 | B71: eCDW | G71: X | I71: N | J71: N | K71: N | M71: Potential Candidate | P71: Potential/needs review (3Q)
A72: 27833 | B72: eCDW Ver - TDATA | D72: X | I72: N | J72: N | K72: N | L72: N | M72: Not a candidate | N72: 0 | P72: Funded to retire
A73: 19101 | B73: ECM P8 | E73: X | I73: Y | J73: Y | K73: N | L73: Y | M73: Onboarded | N73: 0 | O73: configured in lightstep | P73: TAPM onboarded
A74: 10101 | B74: ECO Suite | D74: X | E74: X | I74: Y | J74: N | K74: N | L74: Y | M74: Not a candidate | N74: Fully Onboarded | O74: not available in lightstep | P74: T-Trace onboarded
A75: 34361 | B75: ECO USP | E75: X | I75: Y | J75: N | K75: N | L75: Y | M75: Potential Candidate | N75: Fully Onboarded | O75: not available in lightstep | P75: T-Trace onboarded
A76: 28024 | B76: ECRMI | D76: X | I76: N | J76: N | K76: N | L76: N | M76: Potential Candidate | N76: 0 | P76: Potential/needs review (3Q)
A77: 27531 | B77: Digital IDP | C77: X | D77: X | I77: N | J77: Y | K77: Y | L77: Y | M77: Onboarded | N77: 0 | P77: T-Stack Advanced (Dynatrace)
A78: 19062 | B78: EDGE | D78: X | E78: X | I78: Y | J78: Y | K78: N | L78: Y | M78: Onboarded | N78: Fully Onboarded | O78: configured in lightstep | P78: TAPM & T-Trace onboarded
A79: 18211 | B79: EDP | C79: X | D79: X | I79: Y | J79: Y | K79: N | L79: Y | M79: Onboarded | N79: Fully Onboarded | O79: configured in lightstep | P79: TAPM & T-Trace onboarded
A80: 18263 | B80: Enabler - C | C80: X | I80: N | J80: Y | K80: N | L80: N | M80: Onboarded | N80: 0 | O80: Yet to configure in lightStep | P80: TAPM onboarded
A81: 9899 | B81: Enabler LS | E81: X | I81: Y | J81: Y | K81: N | L81: Y | M81: Onboarded | N81: 0 | O81: configured in lightstep | P81: TAPM onboarded / out of scope for T-Trace
A82: 13537 | B82: End-to-end Flow through Management System
A83: 18284 | B83: ERBI | G83: X | I83: N | J83: N | K83: N | M83: Potential Candidate | P83: Potential/needs review (3Q)
A84: 6169 | B84: ESS | E84: X | I84: Y | J84: Y | K84: N | L84: Y | M84: Onboarded | N84: Client Kick off | O84: configured in lightstep | P84: TAPM onboarded
A85: 9313 | B85: eTRACS | D85: X | I85: Y | J85: Y | K85: N | L85: Y | M85: Onboarded | N85: 0 | O85: configured in lightstep | P85: TAPM onboarded
A86: 31529 | B86: EXFOWorx | E86: X | I86: N | J86: N | K86: N | L86: N | M86: Potential Candidate | N86: 0 | P86: Potential/needs review (3Q)
A87: 19705 | B87: FORCE-DCOE | D87: X | E87: X | I87: Y | J87: Y | K87: N | L87: Y | M87: Onboarded | N87: 0 | O87: configured in lightstep | P87: TAPM onboarded
A88: 24444 | B88: FRVT | E88: X | I88: Y | J88: Y | K88: N | L88: Y | M88: Onboarded | N88: 0 | O88: configured in lightstep | P88: TAPM onboarded
A89: 10417 | B89: G2 | E89: X | I89: Y | J89: N | K89: N | L89: Y | M89: Potential Candidate | N89: Fully Onboarded | O89: not available in lightstep | P89: T-Trace onboarded
A90: 16627 | B90: GCAS Web | E90: X | I90: Y | J90: Y | K90: N | L90: Y | M90: Onboarded | N90: Fully Onboarded | O90: not available in lightstep | P90: TAPM & T-Trace onboarded
A91: 17784 | B91: GEARS | I91: Y | J91: Y | K91: N | M91: Onboarded | N91: Prod in Progress | O91: Yet to configure in lightStep | P91: TAPM & T-Trace onboarded
A92: 9723 | B92: GRANITE | E92: X | I92: Y | J92: Y | K92: N | L92: Y | M92: Onboarded | N92: Potential Candidate | O92: configured in lightstep | P92: TAPM onboarded
A93: 22510 | B93: GRID-AC | D93: X | F93: X | I93: Y | J93: Y | K93: N | L93: Y | M93: Onboarded | N93: Fully Onboarded | O93: configured in lightstep | P93: TAPM & T-Trace onboarded
A94: 22509 | B94: GRID-GDDN | C94: X | G94: X | I94: N | J94: Y | K94: N | L94: N | M94: Onboarded | N94: Not a Candidate | O94: Yet to configure in lightStep | P94: TAPM onboarded
A95: 29349 | B95: GRP-ICAP | C95: X | D95: X | I95: N | J95: Y | K95: N | L95: N | M95: In Progress | N95: 0 | P95: Potential/needs review (3Q)
A96: 27460 | B96: Halo.C AM | D96: X | F96: X | I96: Y | J96: Y | K96: N | L96: Y | M96: Onboarded | N96: 0 | O96: configured in lightstep | P96: TAPM onboarded
A97: 26224 | B97: Halo.E AM | D97: X | E97: X | I97: Y | J97: Y | K97: N | L97: Y | M97: Onboarded | N97: 0 | O97: configured in lightstep | P97: TAPM onboarded
A98: 29243 | B98: HVD-VDI | D98: X | I98: N | J98: N | K98: N | L98: N | M98: Potential Candidate | N98: 0 | P98: Potential/needs review (3Q)
A99: 29607 | B99: CPOP | C99: X | I99: N | J99: N | K99: Y | L99: Y | M99: Not a candidate | N99: Blocked | P99: T-Stack Advanced (Dynatrace)
A100: 30063 | B100: IDP- Chat VA ANDi | D100: X | I100: N | J100: N | K100: Y | L100: Y | M100: Not a candidate | N100: 0 | P100: T-Stack Advanced (Dynatrace)
...

Sheet App & API Tracking
A1: business_flow | B1: e2eux | C1: correlation_id | D1: application | E1: API Gap | F1: EASE resource | M1: Unique Applications
A2: Consumer Broadband Install | B2: Install Buried Drop Request | C2: 27267 | D2: (FED) - FASTBPM | M2: (FED) - FASTBPM
A3: Activation & Provisioning | B3: Market & Service Area Validation | C3: 24095 | D3: (FED) - GEARS | M3: (FED) - GEARS
A4: Activation & Provisioning | B4: Activate | C4: 24095 | D4: (FED) - GEARS | M4: (FED) - TDICE
A5: TechFast | B5: Agent Troubleshoot | C5: 23730 | D5: (FED) - TDICE | M5: 5520 AMS
A6: Provision/Activation | B6: Test Light @ PFP | C6: 10097 | D6: 5520 AMS | M6: AA
A7: Provision/Activation | B7: Connect ONT | C7: 10097 | D7: 5520 AMS | M7: ABPT
A8: Provision/Activation | B8: Verify Correct ONT for Activation | C8: 10097 | D8: 5520 AMS | M8: Amp-MM - Invenio
A9: Billing Inquiry | B9: Notes Auto Summarization | C9: 30176 | D9: AA | M9: Atlas-UI
A10: Add A Line | B10: Notes Auto Summarization | C10: 30176 | D10: AA | M10: ATT CCT AEP
A11: New Customer | B11: Notes Auto Summarization | C11: 30176 | D11: AA | M11: ATT CCT APIGEE
A12: Activation | B12: Notes Auto Summarization | C12: 30176 | D12: AA | M12: ATT CCT Service Access Gateway
A13: Consumer Broadband Install | B13: Qualify to Terminal/Verify Assignments | C13: 18781 | D13: ABPT | M13: ATT Coral Desktop
... A18: TechFast | B18: Agent Troubleshoot | C18: 22827 | D18: Amp-MM - Invenio | M18: BBNMS-SE
A19: Consumer Broadband Install | B19: Review Jobs | C19: 28619 | D19: Atlas-UI | E19: POG app - no API call | M19: BWSFMC
A20: Consumer Broadband Install | B20: Select Job/View Comments | C20: 28619 | D20: Atlas-UI | E20: POG app - no API call | M20: CAP
A21: Consumer Broadband Install | B21: Arrive on Prem/Update Job | C21: 28619 | D21: Atlas-UI | E21: POG app - no API call | M21: CAPM
A22: Consumer Broadband Install | B22: Review Order w/Customer | C22: 28619 | D22: Atlas-UI | E22: POG app - no API call | M22: CAS
A23: Consumer Broadband Install | B23: Qualify to Terminal/Verify Assignments | C23: 28619 | D23: Atlas-UI | E23: POG app - no API call | M23: CAST
A24: Consumer Broadband Install | B24: True Test/Qualify Terminal | C24: 28619 | D24: Atlas-UI | E24: POG app - no API call | M24: CCDL
A25: Consumer Broadband Install | B25: Place Fiber Connectors | C25: 28619 | D25: Atlas-UI | E25: POG app - no API call | M25: CCM, Clarify, CM
A26: Consumer Broadband Install | B26: Add Port to Door | C26: 28619 | D26: Atlas-UI | E26: POG app - no API call | M26: CCMULE
A27: Consumer Broadband Install | B27: Install Fiber Jack | C27: 28619 | D27: Atlas-UI | E27: POG app - no API call | M27: CCMule-CLM
A28: Consumer Broadband Install | B28: Test Light Levels | C28: 28619 | D28: Atlas-UI | E28: POG app - no API call | M28: CCMule-Service
A29: Consumer Broadband Install | B29: Select ONT | C29: 28619 | D29: Atlas-UI | E29: POG app - no API call | M29: CCR-Relational - CCR-R
A30: Consumer Broadband Install | B30: Check Port | C30: 28619 | D30: Atlas-UI | E30: POG app - no API call | M30: CCSF
... A48: Provision/Activation | B48: Mark Job Complete | C48: 28619 | D48: Atlas-UI | E48: POG app - no API call | M48: DTV-ASMM
A49: TechFast | B49: Log Into Device | C49: 28619 | D49: Atlas-UI | M49: eCDW
A50: TechFast | B50: View Job (Technician) | C50: 28619 | D50: Atlas-UI | E50: POG app - no API call | M50: eCDW Ver - TDATA
A51: Troubleshoot /Repair | B51: Review Jobs | C51: 28619 | D51: Atlas-UI | E51: POG app - no API call | M51: ECM P8
A52: Troubleshoot /Repair | B52: Select Job/View Comments | C52: 28619 | D52: Atlas-UI | E52: POG app - no API call | M52: ECO Suite
A53: Troubleshoot /Repair | B53: Arrive on Prem/Update Job | C53: 28619 | D53: Atlas-UI | E53: POG app - no API call | M53: ECO USP
A54: Troubleshoot /Repair | B54: Review Order w/Customer | C54: 28619 | D54: Atlas-UI | E54: POG app - no API call | M54: ECRMI
A55: Troubleshoot /Repair | B55: Isolate & Resolve | C55: 28619 | D55: Atlas-UI | E55: POG app - no API call | M55: EDGE
A56: Troubleshoot /Repair | B56: Create & Submit Damage Claim | C56: 28619 | D56: Atlas-UI | E56: POG app - no API call | M56: Enabler - C
A57: Troubleshoot /Repair | B57: Submit Bury Request | C57: 28619 | D57: Atlas-UI | E57: POG app - no API call | M57: Enabler LS
A58: Troubleshoot /Repair | B58: Quality Check/True Test | C58: 28619 | D58: Atlas-UI | E58: POG app - no API call | M58: ERBI
A59: Troubleshoot /Repair | B59: Close Job | C59: 28619 | D59: Atlas-UI | E59: POG app - no API call | M59: eTRACS
A60: Provision/Disconnect | B60: Review Job | C60: 28619 | D60: Atlas-UI | E60: POG app - no API call | M60: EXFOWorx
A61: Provision/Disconnect | B61: Select Job/View Comments | C61: 28619 | D61: Atlas-UI | E61: POG app - no API call | M61: FORCE-DCOE
... A75: Provision/Disconnect | B75: Mark Job Complete | C75: 28619 | D75: Atlas-UI | E75: POG app - no API call | M75: IDP-Commerce-Cart&Pricing
A76: Billing Inquiry | B76: Billing Inquiry via IVR + Routing | C76: 26150 | D76: ATT CCT AEP | M76: IDP-Commerce-Enabler Services
A77: LiveInFive/CallBack | B77: IVR Menu | C77: 26150 | D77: ATT CCT AEP | M77: IDP-Customer Graph Cloud
A78: Add A Line | B78: IVR Menu + Retrieve Customer Info & Call Routing | C78: 26150 | D78: ATT CCT AEP | M78: IDP-IDM
A79: New Customer | B79: IVR Menu + Retrieve Customer Info & Call Routing | C79: 26150 | D79: ATT CCT AEP | M79: IDP-Order Graph Cloud
A80: Activation | B80: IVR Menu + Retrieve Customer Info & Call Routing | C80: 26150 | D80: ATT CCT AEP | M80: IDP-Platform
A81: Billing Inquiry | B81: Billing Inquiry via IVR + Routing | C81: 30793 | D81: ATT CCT APIGEE | M81: IDP-Upper Funnel Cloud
A82: LiveInFive/CallBack | B82: Retrieve Cust Info & Call Routing | C82: 30793 | D82: ATT CCT APIGEE | M82: IDP-WebAcctMgmt
A83: Add A Line | B83: IVR Menu + Retrieve Customer Info & Call Routing | C83: 30793 | D83: ATT CCT APIGEE | M83: IDP-Web-Sales
A84: New Customer | B84: IVR Menu + Retrieve Customer Info & Call Routing | C84: 30793 | D84: ATT CCT APIGEE | M84: Infor
A85: Activation | B85: IVR Menu + Retrieve Customer Info & Call Routing | C85: 30793 | D85: ATT CCT APIGEE | M85: INLAP
A86: Billing Inquiry | B86: Billing Inquiry via IVR + Routing | C86: 26215 | D86: ATT CCT Service Access Gateway | M86: Intune
A87: LiveInFive/CallBack | B87: IVR Menu | C87: 26215 | D87: ATT CCT Service Access Gateway | M87: ISAAC WFE
... A131: TechFast | B131: Customer Confirmation (SMS) | C131: 33686 | D131: CCMule-CLM | M131: YODA
A132: TechFast | B132: Create Appointment | C132: 33688 | D132: CCMule-Service
A133: Activation & Provisioning | B133: Activate | C133: 19166 | D133: CCR-Relational - CCR-R
A134: MVNO Care | B134: Device or Equipment Issues | C134: 19166 | D134: CCR-Relational - CCR-R
A135: Billing Inquiry | B135: Billing Inquiry via IVR + Routing | C135: 30685 | D135: CCSF | E135: POG app - no API call
A136: Billing Inquiry | B136: IVR to Agent Handoff | C136: 30685 | D136: CCSF | E136: POG app - no API call
A137: Billing Inquiry | B137: Customer Lookup | C137: 30685 | D137: CCSF | E137: POG app - no API call
A138: Billing Inquiry | B138: Customer Billing History | C138: 30685 | D138: CCSF
A139: Billing Inquiry | B139: View Bill | C139: 30685 | D139: CCSF
A140: Billing Inquiry | B140: Recap Call | C140: 30685 | D140: CCSF | E140: POG app - no API call
A141: LiveInFive/CallBack | B141: IVR to Agent Handoff | C141: 30685 | D141: CCSF | E141: POG app - no API call
A142: LiveInFive/CallBack | B142: Customer Lookup | C142: 30685 | D142: CCSF | E142: POG app - no API call
A143: Add A Line | B143: IVR Menu + Retrieve Customer Info & Call Routing | C143: 30685 | D143: CCSF | E143: POG app - no API call
A144: Add A Line | B144: IVR to Agent Handoff | C144: 30685 | D144: CCSF | E144: POG app - no API call
A145: Add A Line | B145: Customer Lookup | C145: 30685 | D145: CCSF | E145: POG app - no API call
A146: Add A Line | B146: Recap Call | C146: 30685 | D146: CCSF | E146: POG app - no API call
A147: TechFast | B147: Customer Lookup | C147: 30685 | D147: CCSF | E147: POG app - no API call
A148: New Customer | B148: IVR to Agent Handoff | C148: 30685 | D148: CCSF | E148: POG app - no API call
A149: New Customer | B149: Create New Customer | C149: 30685 | D149: CCSF | E149: POG app - no API call
A150: New Customer | B150: Search Customer Service Address | C150: 30685 | D150: CCSF | E150: POG app - no API call
A151: New Customer | B151: View Services Available to Customer + Create Account | C151: 30685 | D151: CCSF | E151: POG app - no API call
... A168: Activate New AIA Customer | B168: Review & Submit Order | C168: 30685 | D168: CCSF | E168: POG app - no API call
A169: Billing Inquiry | B169: Billing Inquiry via IVR + Routing | C169: 25363 | D169: CCT ATT IPCS
A170: LiveInFive/CallBack | B170: IVR Menu | C170: 25363 | D170: CCT ATT IPCS
A171: Add A Line | B171: IVR Menu + Retrieve Customer Info & Call Routing | C171: 25363 | D171: CCT ATT IPCS
A172: New Customer | B172: IVR Menu + Retrieve Customer Info & Call Routing | C172: 25363 | D172: CCT ATT IPCS
A173: Activation | B173: IVR Menu + Retrieve Customer Info & Call Routing | C173: 25363 | D173: CCT ATT IPCS
A174: TechFast | B174: Customer Confirmation (SMS) | C174: 30169 | D174: CEP
A175: Tech Support | B175: Live Support | C175: 23872 | D175: Chat
A176: Tech Support | B176: Post-Support Follow Up | C176: 23872 | D176: Chat
A177: New Hire Payroll | B177: Payroll to General Ledger | C177: 32412 | D177: CorpFin-GL
A178: New Hire Payroll | B178: Journalization | C178: 32412 | D178: CorpFin-GL
A179: Upgrade/Trade-In Device | B179: Configure Account | C179: 17765 | D179: CPC
A180: Nat.Dist. - Buy Wireless | B180: Select Device | C180: 17765 | D180: CPC
... A407: Add A Line | B407: IVR Menu + Retrieve Customer Info & Call Routing | C407: 18257 | D407: OPUS - C
A408: New Customer | B408: Create New Customer | C408: 18257 | D408: OPUS - C | E408: POG app - no API call
A409: New Customer | B409: View Services Available to Customer + Create Account | C409: 18257 | D409: OPUS - C | E409: POG app - no API call
A410: New Customer | B410: Port Number | C410: 18257 | D410: OPUS - C | E410: POG app - no API call
A411: New Customer | B411: Credit Check | C411: 18257 | D411: OPUS - C | E411: POG app - no API call
A412: New Customer | B412: Bundle Builder - Select Phones | C412: 18257 | D412: OPUS - C | E412: POG app - no API call
A413: New Customer | B413: Number Selection | C413: 18257 | D413: OPUS - C | E413: POG app - no API call
A414: New Customer | B414: Set Up Paperless Billing / Autopay | C414: 18257 | D414: OPUS - C | E414: POG app - no API call
A415: New Customer | B415: Fraud Check | C415: 18257 | D415: OPUS - C | E415: POG app - no API call
A416: New Customer | B416: Payment & Complete Sale | C416: 18257 | D416: OPUS - C | E416: POG app - no API call
A417: Activation | B417: Search Customer Service Address | C417: 18257 | D417: OPUS - C | E417: POG app - no API call
A418: Activation | B418: Skip Trade In | C418: 18257 | D418: OPUS - C | E418: POG app - no API call
A419: Activation | B419: Payment Page | C419: 18257 | D419: OPUS - C | E419: POG app - no API call
...

Sheet Detail1
A1: Details for Count of application - channel: Online, api: (blank)
A3: editor | B3: action | C3: lineOfBusiness | D3: channel | E3: product | F3: domain_sequence | G3: domain | H3: sub_domain_sequence | I3: subdomain | J3: business_flow_sequence | K3: business_flow | L3: e2eux_sequence | M3: sequence_uml | N3: e2eux | O3: correlation_id | P3: application | Q3: api
A4: tm0828 | B4: Add | C4: Mass Markets | D4: Online | E4: Mobility | F4: 1 | G4: Shop & Purchase | H4: 5 | I4: Checkout | J4: 1 | K4: Purchase Product | L4: 13 | M4: IDP-Web-Sales ->> IDP-IDM : API IDP-Web-Sales ->> TLG-MOB : API IDP-Web-Sales ->> IDP BUPS : updateBillingInformation | N4: Enter Billing Information | O4: 18193 | P4: TLG-MOB
A5: tm0828 | B5: Add | C5: Mass Markets | D5: Online | E5: Mobility | F5: 1 | G5: Shop & Purchase | H5: 1 | I5: Learn & Discover | J5: 3 | K5: Apply Promotions | L5: 1 | M5: TLG-MOB ->> notifyNow : API | N5: Send Promotional Offer to Customer | O5: 18193 | P5: TLG-MOB
A6: tm0828 | B6: Add | C6: Mass Markets | D6: Online | E6: Mobility | F6: 1 | G6: Shop & Purchase | H6: 1 | I6: Learn & Discover | J6: 3 | K6: Apply Promotions | L6: 1 | M6: TLG-MOB ->> notifyNow : API | N6: Send Promotional Offer to Customer | O6: 30920 | P6: notifyNow
A7: tm0828 | B7: Add | C7: Mass Markets | D7: Online | E7: Mobility | F7: 1 | G7: Shop & Purchase | H7: 5 | I7: Checkout | J7: 4 | K7: Upgrade Device | L7: 9 | M7: IDP-Web-Sales ->> IDP-Commerce-Cart&Pricing : api_name_here IDP-Web-Sales ->> IDP-WebAcctMgmt : api_name_here IDP-Commerce-Cart&Pricing ->> IDP-Cart-and-Checkout-UI : api_name_here | N7: Checkout | O7: 33758 | P7: IDP-Web-Sales
A8: tm0828 | B8: Add | C8: Mass Markets | D8: Online | E8: Mobility | F8: 1 | G8: Shop & Purchase | H8: 5 | I8: Checkout | J8: 1 | K8: Purchase Product | L8: 13 | M8: IDP-Web-Sales ->> IDP-IDM : API IDP-Web-Sales ->> TLG-MOB : API IDP-Web-Sales ->> IDP BUPS : updateBillingInformation | N8: Enter Billing Information | O8: 33758 | P8: IDP-Web-Sales
A9: tm0828 | B9: Add | C9: Mass Markets | D9: Online | E9: Mobility | F9: 1 | G9: Shop & Purchase | H9: 5 | I9: Checkout | J9: 1 | K9: Purchase Product | L9: 12 | M9: IDP-Web-Sales ->> IDP-Commerce-Cart&Pricing : api_name_here IDP-Web-Sales ->> IDP-WebAcctMgmt : api_name_here IDP-Commerce-Cart&Pricing ->> IDP-Cart-and-Checkout-UI : api_name_here | N9: Checkout | O9: 33758 | P9: IDP-Web-Sales
A10: tm0828 | B10: Add | C10: Mass Markets | D10: Online | E10: Mobility | F10: 1 | G10: Shop & Purchase | H10: 1 | I10: Learn & Discover | J10: 1 | K10: Purchase Product | L10: 2 | M10: UI ->> IDP Upper Funnel Cloud : CPOP Offers MS IDP Upper Funnel Cloud ->> PLP : online-sales-orchestration IDP Upper Funnel Cloud ->> IDP Web Sales : API | N10: Select "Wireless" | O10: 33758 | P10: IDP-Web-Sales
A11: tm0828 | B11: Add | C11: Mass Markets | D11: Online | E11: Mobility | F11: 3 | G11: Use & Manage | H11: 2 | I11: Change Plan / Change Speed | J11: 2 | K11: Manage Account | L11: 16 | M11: IDP Upper Funnel Cloud ->> IDP WebAcctMgmt : /msapi/wirelessplanmgmt/v1/compare IDP Upper Funnel Cloud ->> IDP Web Sales : API IDP Upper Funnel Cloud ->> IDP-Commerce-Cart&Pricing : API | N11: Compare and Select Wireless Plan | O11: 33758 | P11: IDP-Web-Sales
A12: tm0828 | B12: Add | C12: Mass Markets | D12: Online | E12: Mobility | F12: 1 | G12: Shop & Purchase | H12: 5 | I12: Checkout | J12: 4 | K12: Upgrade Device | L12: 9 | M12: IDP-Web-Sales ->> IDP-Commerce-Cart&Pricing : api_name_here IDP-Web-Sales ->> IDP-WebAcctMgmt : api_name_here IDP-Commerce-Cart&Pricing ->> IDP-Cart-and-Checkout-UI : api_name_here | N12: Checkout | O12: 32768 | P12: IDP-WebAcctMgmt
A13: tm0828 | B13: Add | C13: Mass Markets | D13: Online | E13: Mobility | F13: 1 | G13: Shop & Purchase | H13: 5 | I13: Checkout | J13: 1 | K13: Purchase Product | L13: 12 | M13: IDP-Web-Sales ->> IDP-Commerce-Cart&Pricing : api_name_here IDP-Web-Sales ->> IDP-WebAcctMgmt : api_name_here IDP-Commerce-Cart&Pricing ->> IDP-Cart-and-Checkout-UI : api_name_here | N13: Checkout | O13: 32768 | P13: IDP-WebAcctMgmt
A14: tm0828 | B14: Add | C14: Mass Markets | D14: Online | E14: Mobility | F14: 1 | G14: Shop & Purchase | H14: 5 | I14: Checkout | J14: 3 | K14: Apply Promotions | L14: 8 | M14: IDP-Web-Sales ->> IDP-Commerce-Cart&Pricing : API IDP-Web-Sales ->> IDP-WebAcctMgmt : API IDP-Commerce-Cart&Pricing ->> IDP-Cart-and-Checkout-UI : API | N14: Checkout | O14: 32768 | P14: IDP-WebAcctMgmt
A15: tm0828 | B15: Add | C15: Mass Markets | D15: Online | E15: Mobility | F15: 2 | G15: Onboard & Activate | H15: 1 | I15: Receive Products | J15: 4 | K15: Upgrade Device | L15: 10 | M15: UI ->> IDP Upper Funnel Cloud : API IDP Upper Funnel Cloud ->> IDP Web Sales : Send Purchase Confirmation IDP Web Sales ->> OCE : Order Submitted OCE ->> YODA : Order Information for Fulfillment | N15: Schedule Device Delivery / Pickup | O15: 31548 | P15: IDP-Upper Funnel Cloud
... A63: tm0828 | B63: Add | C63: Mass Markets | D63: Online | E63: Mobility | F63: 4 | G63: Service & Support | H63: 3 | I63: Resolve Issue | J63: 6 | K63: Get Technical Support | L63: 5 | M63: UI ->> IDP Upper Funnel Cloud : API IDP Upper Funnel Cloud ->> IDP Web Support : /msapi/idp-content-orchestration/v1/scms/support/web-support/robocalldetails IDP Upper Funnel Cloud ->> IDP Web Support : /msapi/idp-content-orchestration/v1/scms/support/pages/report-call-or-text IDP Web Support ->> Chat : API IDP Upper Funnel Cloud ->> Chat : API Chat ->> GRID-AC : API Chat ->> AVT : API | N63: Get Live Support | O63: 19105 | P63: AVT

Sheet Sheet1
